EE1501_DSLab/project/final/traffic_light_controller/main.v
`timescale 1s/1ms

// traffic_light_controller.v
module traffic_light_controller(
    input            clk,
    input            reset,
    input            Emergency_Left,
    input            Emergency_Right,
    output reg [1:0] T1,        // 00:G, 01:Y, 10:R
    output reg [1:0] T2,        // 00:G, 01:Y, 10:R
    output reg       T1_WALK,
    output reg       T2_WALK,
    output reg       buzzer1,
    output reg       buzzer2
    );

    // State encoding
    localparam S1 = 3'd1,
               S2 = 3'd2,
               S3 = 3'd3,
               S4 = 3'd4,
               S5 = 3'd5,
               S6 = 3'd6;

    // Timing constants (in clock ticks)
    localparam T_S1 = 29,
               T_S2 =  4,
               T_S3 = 19,
               T_S4 =  4,
               T_S5 = 29,
               T_S6 =  4,
               T_EM =  9;

    localparam GREEN  = 2'b00,
               RED    = 2'b10,
               YELLOW = 2'b01;

    reg [2:0] current_state, next_state;
    reg [6:0] timer, emergency_timer;
    reg emergency_right_active, emergency_left_active;

    // State register + outputs reset
    always @(posedge clk or posedge reset) begin
        if (reset) begin
            current_state   <= S1;
            timer           <= 0;
            emergency_timer <= 0;
            emergency_right_active <= 0;
            emergency_left_active <= 0;
            T1       <= GREEN;
            T2       <= RED;
            T1_WALK  <= 1'b0;
            T2_WALK  <= 1'b0;
            buzzer1  <= 1'b0;
            buzzer2  <= 1'b0;
        end else begin
            // ----- Emergency priority -----
            case (emergency_right_active | emergency_left_active | Emergency_Left | Emergency_Right)
              1'b1: begin
                // first, check Right (priority)
                case (emergency_right_active | Emergency_Right)
                  1'b1: begin
                    // Set active flag when emergency signal is detected
                    case (Emergency_Right)
                      1'b1: emergency_right_active <= 1'b1;
                      default: begin end
                    endcase
                    
                    // Check if emergency should continue
                    case (emergency_timer < T_EM)
                      1'b1: emergency_timer <= emergency_timer + 1;
                      default: begin
                        // Timer hit 10 seconds, check emergency signal again
                        case (Emergency_Right)
                          1'b1: emergency_timer <= 0; // restart timer
                          default: begin
                            emergency_timer <= 0;
                            emergency_right_active <= 0;
                          end
                        endcase
                      end
                    endcase
                    
                    // Set outputs for right emergency
                    T1       <= RED;
                    T2       <= RED;
                    T1_WALK  <= 1'b0;
                    T2_WALK  <= 1'b0;
                    buzzer1  <= 1'b0;
                    buzzer2  <= 1'b0;
                  end
                  
                  default: begin
                    // then, if not Right, check Left
                    case (emergency_left_active | Emergency_Left)
                      1'b1: begin
                        // Set active flag when emergency signal is detected
                        case (Emergency_Left)
                          1'b1: emergency_left_active <= 1'b1;
                          default: begin end
                        endcase
                        
                        // Check if emergency should continue
                        case (emergency_timer < T_EM)
                          1'b1: emergency_timer <= emergency_timer + 1;
                          default: begin
                            // Timer hit 10 seconds, check emergency signal again
                            case (Emergency_Left)
                              1'b1: emergency_timer <= 0; // restart timer
                              default: begin
                                emergency_timer <= 0;
                                emergency_left_active <= 0;
                              end
                            endcase
                          end
                        endcase
                        
                        // Set outputs for left emergency
                        T1       <= RED;
                        T2       <= GREEN;
                        T1_WALK  <= 1'b0;
                        T2_WALK  <= 1'b0;
                        buzzer1  <= 1'b0;
                        buzzer2  <= 1'b0;
                      end
                      default: begin end
                    endcase
                  end
                endcase
              end

              // ----- Normal operation -----
              default: begin
                case (current_state)
                  S1: begin
                    T1_WALK <= 1'b0 ; T2_WALK <= 1'b1; buzzer1 <= 1'b0;
                    T1      <= GREEN; T2      <= RED ; buzzer2 <= 1'b0;
                    case (timer < T_S1)
                      1'b1: timer <= timer + 1;
                      default: begin
                        timer         <= 0;
                        current_state <= S2;
                      end
                    endcase
                  end
                  S2: begin
                    T1_WALK <= 1'b0  ; T2_WALK <= 1'b1; buzzer1 <= 1'b0;
                    T1      <= YELLOW; T2      <= RED ; buzzer2 <= 1'b0;
                    case (timer < T_S2)
                      1'b1: timer <= timer + 1;
                      default: begin
                        timer         <= 0;
                        current_state <= S3;
                      end
                    endcase
                  end
                  S3: begin
                    T1_WALK <= 1'b1; T2_WALK <= 1'b1; buzzer1 <= 1'b0;
                    T1      <= RED ; T2      <= RED ; buzzer2 <= 1'b0;
                    case (timer < T_S3)
                      1'b1: timer <= timer + 1;
                      default: begin
                        timer         <= 0;
                        current_state <= S4;
                      end
                    endcase
                  end
                  S4: begin
                    T1_WALK <= 1'b1; T2_WALK <= 1'b1; buzzer1 <= 1'b0;
                    T1      <= RED ; T2      <= RED ; buzzer2 <= 1'b1;
                    case (timer < T_S4)
                      1'b1: timer <= timer + 1;
                      default: begin
                        timer         <= 0;
                        current_state <= S5;
                      end
                    endcase
                  end
                  S5: begin
                    T1_WALK <= 1'b1; T2_WALK <= 1'b0 ; buzzer1 <= 1'b0;
                    T1      <= RED ; T2      <= GREEN; buzzer2 <= 1'b0;
                    case (timer < T_S5)
                      1'b1: timer <= timer + 1;
                      default: begin
                        timer         <= 0;
                        current_state <= S6;
                      end
                    endcase
                  end
                  S6: begin
                    T1_WALK <= 1'b1; T2_WALK <= 1'b0  ; buzzer1 <= 1'b1;
                    T1      <= RED ; T2      <= YELLOW; buzzer2 <= 1'b0;
                    case (timer < T_S6)
                      1'b1: timer <= timer + 1;
                      default: begin
                        timer         <= 0;
                        current_state <= S1;
                      end
                    endcase
                  end
                  default: current_state <= S1;
                endcase
              end
            endcase
        end
    end

    // Next-state logic (unchanged)
    always @(*) begin
        case (current_state)
            S1: next_state = S2;
            S2: next_state = S3;
            S3: next_state = S4;
            S4: next_state = S5;
            S5: next_state = S6;
            S6: next_state = S1;
            default: next_state = S1;
        endcase
    end

endmodule

EE1501_DSLab/project/final/traffic_light_controller/main_tb.v
`timescale 1s/1ms

module tb_traffic_light_controller;

    reg clk, reset;
    reg Emergency_Left, Emergency_Right;
    wire [1:0] T1, T2;
    wire T1_WALK, T2_WALK, buzzer1, buzzer2;

    // Instantiate your module
    traffic_light_controller uut (
        .clk(clk),
        .reset(reset),
        .Emergency_Left(Emergency_Left),
        .Emergency_Right(Emergency_Right),
        .T1(T1),
        .T2(T2),
        .T1_WALK(T1_WALK),
        .T2_WALK(T2_WALK),
        .buzzer1(buzzer1),
        .buzzer2(buzzer2)
    );

    // Clock generation
    initial begin
        clk = 0;
        forever #0.5 clk = ~clk;
    end

    // Light name string variables (for display)
    reg [8*6:1] T1_str, T2_str;

    always @* begin
        case (T1)
            2'b00: T1_str = "GREEN ";
            2'b01: T1_str = "YELLOW";
            2'b10: T1_str = "RED   ";
            default: T1_str = "UNKWN ";
        endcase

        case (T2)
            2'b00: T2_str = "GREEN ";
            2'b01: T2_str = "YELLOW";
            2'b10: T2_str = "RED   ";
            default: T2_str = "UNKWN ";
        endcase
    end

    // Print when anything changes
    initial begin
        $monitor("Time: %0d | T1: %s | T2: %s | T1_WALK = %b | T2_WALK = %b | Buzzer1 = %b | Buzzer2 = %b | E_Left = %b | E_Right = %b",
                 $time, T1_str, T2_str, T1_WALK, T2_WALK, buzzer1, buzzer2, Emergency_Left, Emergency_Right);
    end

    // Stimulus
    integer i;
    initial begin
        // Start VCD file generation
        $dumpfile("wave.vcd");
        $dumpvars(0, tb_traffic_light_controller);
        
        $display("\n=== T-Junction Traffic Light Controller Simulation Started ===\n");

        Emergency_Left = 0;
        Emergency_Right = 0;
        reset = 1;
        #1;
        reset = 0;
        $display("=== Reset at t=%0d ===", $time);

        // Normal operation - let it go through a complete cycle
        $display("\n=== Normal Operation - Full Cycle ===");
        #100;

        // Test Case 1: Short Emergency Left (< T_EM)
        $display("\n=== Test Case 1: Short Emergency Left (<T_EM) ===");
        Emergency_Left = 1;
        #2;
        Emergency_Left = 0;
        // Wait for emergency to complete (should be T_EM = 9 seconds)
        #15;

        // Test Case 2: Long Emergency Left (> T_EM)
        $display("\n=== Test Case 2: Long Emergency Left (>T_EM) ===");
        Emergency_Left = 1;
        #15;
        Emergency_Left = 0;
        // Wait for emergency to complete
        #15;

        // Test Case 3: Short Emergency Right (< T_EM)
        $display("\n=== Test Case 3: Short Emergency Right (<T_EM) ===");
        Emergency_Right = 1;
        #2;
        Emergency_Right = 0;
        // Wait for emergency to complete (should be T_EM = 9 seconds)
        #15;

        // Test Case 4: Long Emergency Right (> T_EM)
        $display("\n=== Test Case 4: Long Emergency Right (>T_EM) ===");
        Emergency_Right = 1;
        #15;
        Emergency_Right = 0;
        // Wait for emergency to complete
        #15;

        // Test Case 5: Priority test - Both emergencies active, Right should take priority
        $display("\n=== Test Case 5: Priority Test - Both Emergencies Active ===");
        Emergency_Left = 1;
        Emergency_Right = 1;
        #15;
        Emergency_Right = 0;
        #5;
        Emergency_Left = 0;
        // Wait for emergency to complete
        #15;

        // Test Case 6: Overlapping emergencies - Left starts, then Right interrupts
        $display("\n=== Test Case 6: Overlapping Emergencies - Left then Right ===");
        Emergency_Left = 1;
        #5;
        Emergency_Right = 1;
        #5;
        Emergency_Left = 0;
        #5;
        Emergency_Right = 0;
        // Wait for emergency to complete
        #15;

        // Test Case 7: Overlapping emergencies - Right starts, then Left (should be ignored until Right is done)
        $display("\n=== Test Case 7: Overlapping Emergencies - Right then Left ===");
        Emergency_Right = 1;
        #5;
        Emergency_Left = 1;
        #5;
        Emergency_Right = 0;
        #5;
        Emergency_Left = 0;
        // Wait for emergency to complete
        #15;

        // Test Case 8: Back-to-back emergencies
        $display("\n=== Test Case 8: Back-to-back Emergencies ===");
        Emergency_Right = 1;
        #5;
        Emergency_Right = 0;
        #12; // Just after first emergency ends
        Emergency_Left = 1;
        #5;
        Emergency_Left = 0;
        // Wait for emergency to complete
        #15;

        // Final normal operation
        $display("\n=== Final Normal Operation ===");
        #50;

        $display("\n=== Simulation Complete ===\n");
        $finish;
    end

endmodule

EE1501_DSLab/project/final/traffic_light_controller/wave.vcd
$date
	Thu May  8 00:16:32 2025
$end
$version
	Icarus Verilog
$end
$timescale
	1ms
$end
$scope module tb_traffic_light_controller $end
$var wire 1 ! buzzer2 $end
$var wire 1 " buzzer1 $end
$var wire 1 # T2_WALK $end
$var wire 2 $ T2 [1:0] $end
$var wire 1 % T1_WALK $end
$var wire 2 & T1 [1:0] $end
$var reg 1 ' Emergency_Left $end
$var reg 1 ( Emergency_Right $end
$var reg 48 ) T1_str [48:1] $end
$var reg 48 * T2_str [48:1] $end
$var reg 1 + clk $end
$var reg 1 , reset $end
$scope module uut $end
$var wire 1 ' Emergency_Left $end
$var wire 1 ( Emergency_Right $end
$var wire 1 + clk $end
$var wire 1 , reset $end
$var parameter 2 - GREEN $end
$var parameter 2 . RED $end
$var parameter 3 / S1 $end
$var parameter 3 0 S2 $end
$var parameter 3 1 S3 $end
$var parameter 3 2 S4 $end
$var parameter 3 3 S5 $end
$var parameter 3 4 S6 $end
$var parameter 32 5 T_EM $end
$var parameter 32 6 T_S1 $end
$var parameter 32 7 T_S2 $end
$var parameter 32 8 T_S3 $end
$var parameter 32 9 T_S4 $end
$var parameter 32 : T_S5 $end
$var parameter 32 ; T_S6 $end
$var parameter 2 < YELLOW $end
$var reg 2 = T1 [1:0] $end
$var reg 1 % T1_WALK $end
$var reg 2 > T2 [1:0] $end
$var reg 1 # T2_WALK $end
$var reg 1 " buzzer1 $end
$var reg 1 ! buzzer2 $end
$var reg 3 ? current_state [2:0] $end
$var reg 1 @ emergency_left_active $end
$var reg 1 A emergency_right_active $end
$var reg 7 B emergency_timer [6:0] $end
$var reg 3 C next_state [2:0] $end
$var reg 7 D timer [6:0] $end
$upscope $end
$upscope $end
$enddefinitions $end
$comment Show the parameter values. $end
$dumpall
b1 <
b100 ;
b11101 :
b100 9
b10011 8
b100 7
b11101 6
b1001 5
b110 4
b101 3
b100 2
b11 1
b10 0
b1 /
b10 .
b0 -
$end
#0
$dumpvars
b0 D
b10 C
b0 B
0A
0@
b1 ?
b10 >
b0 =
1,
0+
b10100100100010101000100001000000010000000100000 *
b10001110101001001000101010001010100111000100000 )
0(
0'
b0 &
0%
b10 $
0#
0"
0!
$end
#500
1+
#1000
0+
0,
#1500
b1 D
1#
1+
#2000
0+
#2500
b10 D
1+
#3000
0+
#3500
b11 D
1+
#4000
0+
#4500
b100 D
1+
#5000
0+
#5500
b101 D
1+
#6000
0+
#6500
b110 D
1+
#7000
0+
#7500
b111 D
1+
#8000
0+
#8500
b1000 D
1+
#9000
0+
#9500
b1001 D
1+
#10000
0+
#10500
b1010 D
1+
#11000
0+
#11500
b1011 D
1+
#12000
0+
#12500
b1100 D
1+
#13000
0+
#13500
b1101 D
1+
#14000
0+
#14500
b1110 D
1+
#15000
0+
#15500
b1111 D
1+
#16000
0+
#16500
b10000 D
1+
#17000
0+
#17500
b10001 D
1+
#18000
0+
#18500
b10010 D
1+
#19000
0+
#19500
b10011 D
1+
#20000
0+
#20500
b10100 D
1+
#21000
0+
#21500
b10101 D
1+
#22000
0+
#22500
b10110 D
1+
#23000
0+
#23500
b10111 D
1+
#24000
0+
#24500
b11000 D
1+
#25000
0+
#25500
b11001 D
1+
#26000
0+
#26500
b11010 D
1+
#27000
0+
#27500
b11011 D
1+
#28000
0+
#28500
b11100 D
1+
#29000
0+
#29500
b11101 D
1+
#30000
0+
#30500
b11 C
b10 ?
b0 D
1+
#31000
0+
#31500
b10110010100010101001100010011000100111101010111 )
b1 D
b1 &
b1 =
1+
#32000
0+
#32500
b10 D
1+
#33000
0+
#33500
b11 D
1+
#34000
0+
#34500
b100 D
1+
#35000
0+
#35500
b100 C
b11 ?
b0 D
1+
#36000
0+
#36500
b10100100100010101000100001000000010000000100000 )
b1 D
b10 &
b10 =
1%
1+
#37000
0+
#37500
b10 D
1+
#38000
0+
#38500
b11 D
1+
#39000
0+
#39500
b100 D
1+
#40000
0+
#40500
b101 D
1+
#41000
0+
#41500
b110 D
1+
#42000
0+
#42500
b111 D
1+
#43000
0+
#43500
b1000 D
1+
#44000
0+
#44500
b1001 D
1+
#45000
0+
#45500
b1010 D
1+
#46000
0+
#46500
b1011 D
1+
#47000
0+
#47500
b1100 D
1+
#48000
0+
#48500
b1101 D
1+
#49000
0+
#49500
b1110 D
1+
#50000
0+
#50500
b1111 D
1+
#51000
0+
#51500
b10000 D
1+
#52000
0+
#52500
b10001 D
1+
#53000
0+
#53500
b10010 D
1+
#54000
0+
#54500
b10011 D
1+
#55000
0+
#55500
b101 C
b100 ?
b0 D
1+
#56000
0+
#56500
b1 D
1!
1+
#57000
0+
#57500
b10 D
1+
#58000
0+
#58500
b11 D
1+
#59000
0+
#59500
b100 D
1+
#60000
0+
#60500
b110 C
b101 ?
b0 D
1+
#61000
0+
#61500
b10001110101001001000101010001010100111000100000 *
b1 D
0!
b0 $
b0 >
0#
1+
#62000
0+
#62500
b10 D
1+
#63000
0+
#63500
b11 D
1+
#64000
0+
#64500
b100 D
1+
#65000
0+
#65500
b101 D
1+
#66000
0+
#66500
b110 D
1+
#67000
0+
#67500
b111 D
1+
#68000
0+
#68500
b1000 D
1+
#69000
0+
#69500
b1001 D
1+
#70000
0+
#70500
b1010 D
1+
#71000
0+
#71500
b1011 D
1+
#72000
0+
#72500
b1100 D
1+
#73000
0+
#73500
b1101 D
1+
#74000
0+
#74500
b1110 D
1+
#75000
0+
#75500
b1111 D
1+
#76000
0+
#76500
b10000 D
1+
#77000
0+
#77500
b10001 D
1+
#78000
0+
#78500
b10010 D
1+
#79000
0+
#79500
b10011 D
1+
#80000
0+
#80500
b10100 D
1+
#81000
0+
#81500
b10101 D
1+
#82000
0+
#82500
b10110 D
1+
#83000
0+
#83500
b10111 D
1+
#84000
0+
#84500
b11000 D
1+
#85000
0+
#85500
b11001 D
1+
#86000
0+
#86500
b11010 D
1+
#87000
0+
#87500
b11011 D
1+
#88000
0+
#88500
b11100 D
1+
#89000
0+
#89500
b11101 D
1+
#90000
0+
#90500
b1 C
b110 ?
b0 D
1+
#91000
0+
#91500
b10110010100010101001100010011000100111101010111 *
b1 D
b1 $
b1 >
1"
1+
#92000
0+
#92500
b10 D
1+
#93000
0+
#93500
b11 D
1+
#94000
0+
#94500
b100 D
1+
#95000
0+
#95500
b10 C
b1 ?
b0 D
1+
#96000
0+
#96500
b10100100100010101000100001000000010000000100000 *
b10001110101001001000101010001010100111000100000 )
b1 D
b10 $
b10 >
b0 &
b0 =
0"
1#
0%
1+
#97000
0+
#97500
b10 D
1+
#98000
0+
#98500
b11 D
1+
#99000
0+
#99500
b100 D
1+
#100000
0+
#100500
b101 D
1+
#101000
0+
1'
#101500
b10001110101001001000101010001010100111000100000 *
b10100100100010101000100001000000010000000100000 )
0#
b0 $
b0 >
b10 &
b10 =
b1 B
1@
1+
#102000
0+
#102500
b10 B
1+
#103000
0+
0'
#103500
b11 B
1+
#104000
0+
#104500
b100 B
1+
#105000
0+
#105500
b101 B
1+
#106000
0+
#106500
b110 B
1+
#107000
0+
#107500
b111 B
1+
#108000
0+
#108500
b1000 B
1+
#109000
0+
#109500
b1001 B
1+
#110000
0+
#110500
0@
b0 B
1+
#111000
0+
#111500
b10100100100010101000100001000000010000000100000 *
b10001110101001001000101010001010100111000100000 )
b110 D
b10 $
b10 >
b0 &
b0 =
1#
1+
#112000
0+
#112500
b111 D
1+
#113000
0+
#113500
b1000 D
1+
#114000
0+
#114500
b1001 D
1+
#115000
0+
#115500
b1010 D
1+
#116000
0+
#116500
b1011 D
1+
#117000
0+
#117500
b1100 D
1+
#118000
0+
1'
#118500
b10001110101001001000101010001010100111000100000 *
b10100100100010101000100001000000010000000100000 )
0#
b0 $
b0 >
b10 &
b10 =
b1 B
1@
1+
#119000
0+
#119500
b10 B
1+
#120000
0+
#120500
b11 B
1+
#121000
0+
#121500
b100 B
1+
#122000
0+
#122500
b101 B
1+
#123000
0+
#123500
b110 B
1+
#124000
0+
#124500
b111 B
1+
#125000
0+
#125500
b1000 B
1+
#126000
0+
#126500
b1001 B
1+
#127000
0+
#127500
b0 B
1+
#128000
0+
#128500
b1 B
1+
#129000
0+
#129500
b10 B
1+
#130000
0+
#130500
b11 B
1+
#131000
0+
#131500
b100 B
1+
#132000
0+
#132500
b101 B
1+
#133000
0+
0'
#133500
b110 B
1+
#134000
0+
#134500
b111 B
1+
#135000
0+
#135500
b1000 B
1+
#136000
0+
#136500
b1001 B
1+
#137000
0+
#137500
0@
b0 B
1+
#138000
0+
#138500
b10100100100010101000100001000000010000000100000 *
b10001110101001001000101010001010100111000100000 )
b1101 D
b10 $
b10 >
b0 &
b0 =
1#
1+
#139000
0+
#139500
b1110 D
1+
#140000
0+
#140500
b1111 D
1+
#141000
0+
#141500
b10000 D
1+
#142000
0+
#142500
b10001 D
1+
#143000
0+
#143500
b10010 D
1+
#144000
0+
#144500
b10011 D
1+
#145000
0+
#145500
b10100 D
1+
#146000
0+
#146500
b10101 D
1+
#147000
0+
#147500
b10110 D
1+
#148000
0+
1(
#148500
b10100100100010101000100001000000010000000100000 )
0#
b10 &
b10 =
b1 B
1A
1+
#149000
0+
#149500
b10 B
1+
#150000
0+
0(
#150500
b11 B
1+
#151000
0+
#151500
b100 B
1+
#152000
0+
#152500
b101 B
1+
#153000
0+
#153500
b110 B
1+
#154000
0+
#154500
b111 B
1+
#155000
0+
#155500
b1000 B
1+
#156000
0+
#156500
b1001 B
1+
#157000
0+
#157500
0A
b0 B
1+
#158000
0+
#158500
b10001110101001001000101010001010100111000100000 )
b10111 D
b0 &
b0 =
1#
1+
#159000
0+
#159500
b11000 D
1+
#160000
0+
#160500
b11001 D
1+
#161000
0+
#161500
b11010 D
1+
#162000
0+
#162500
b11011 D
1+
#163000
0+
#163500
b11100 D
1+
#164000
0+
#164500
b11101 D
1+
#165000
0+
1(
#165500
b10100100100010101000100001000000010000000100000 )
0#
b10 &
b10 =
b1 B
1A
1+
#166000
0+
#166500
b10 B
1+
#167000
0+
#167500
b11 B
1+
#168000
0+
#168500
b100 B
1+
#169000
0+
#169500
b101 B
1+
#170000
0+
#170500
b110 B
1+
#171000
0+
#171500
b111 B
1+
#172000
0+
#172500
b1000 B
1+
#173000
0+
#173500
b1001 B
1+
#174000
0+
#174500
b0 B
1+
#175000
0+
#175500
b1 B
1+
#176000
0+
#176500
b10 B
1+
#177000
0+
#177500
b11 B
1+
#178000
0+
#178500
b100 B
1+
#179000
0+
#179500
b101 B
1+
#180000
0+
0(
#180500
b110 B
1+
#181000
0+
#181500
b111 B
1+
#182000
0+
#182500
b1000 B
1+
#183000
0+
#183500
b1001 B
1+
#184000
0+
#184500
0A
b0 B
1+
#185000
0+
#185500
b11 C
b10001110101001001000101010001010100111000100000 )
b10 ?
b0 D
b0 &
b0 =
1#
1+
#186000
0+
#186500
b10110010100010101001100010011000100111101010111 )
b1 D
b1 &
b1 =
1+
#187000
0+
#187500
b10 D
1+
#188000
0+
#188500
b11 D
1+
#189000
0+
#189500
b100 D
1+
#190000
0+
#190500
b100 C
b11 ?
b0 D
1+
#191000
0+
#191500
b10100100100010101000100001000000010000000100000 )
b1 D
b10 &
b10 =
1%
1+
#192000
0+
#192500
b10 D
1+
#193000
0+
#193500
b11 D
1+
#194000
0+
#194500
b100 D
1+
#195000
0+
1(
1'
#195500
0#
0%
b1 B
1A
1+
#196000
0+
#196500
b10 B
1+
#197000
0+
#197500
b11 B
1+
#198000
0+
#198500
b100 B
1+
#199000
0+
#199500
b101 B
1+
#200000
0+
#200500
b110 B
1+
#201000
0+
#201500
b111 B
1+
#202000
0+
#202500
b1000 B
1+
#203000
0+
#203500
b1001 B
1+
#204000
0+
#204500
b0 B
1+
#205000
0+
#205500
b1 B
1+
#206000
0+
#206500
b10 B
1+
#207000
0+
#207500
b11 B
1+
#208000
0+
#208500
b100 B
1+
#209000
0+
#209500
b101 B
1+
#210000
0+
0(
#210500
b110 B
1+
#211000
0+
#211500
b111 B
1+
#212000
0+
#212500
b1000 B
1+
#213000
0+
#213500
b1001 B
1+
#214000
0+
#214500
0A
b0 B
1+
#215000
0+
0'
#215500
b101 D
1#
1%
1+
#216000
0+
#216500
b110 D
1+
#217000
0+
#217500
b111 D
1+
#218000
0+
#218500
b1000 D
1+
#219000
0+
#219500
b1001 D
1+
#220000
0+
#220500
b1010 D
1+
#221000
0+
#221500
b1011 D
1+
#222000
0+
#222500
b1100 D
1+
#223000
0+
#223500
b1101 D
1+
#224000
0+
#224500
b1110 D
1+
#225000
0+
#225500
b1111 D
1+
#226000
0+
#226500
b10000 D
1+
#227000
0+
#227500
b10001 D
1+
#228000
0+
#228500
b10010 D
1+
#229000
0+
#229500
b10011 D
1+
#230000
0+
1'
#230500
b10001110101001001000101010001010100111000100000 *
0#
0%
b0 $
b0 >
b1 B
1@
1+
#231000
0+
#231500
b10 B
1+
#232000
0+
#232500
b11 B
1+
#233000
0+
#233500
b100 B
1+
#234000
0+
#234500
b101 B
1+
#235000
0+
1(
#235500
b10100100100010101000100001000000010000000100000 *
b10 $
b10 >
b110 B
1A
1+
#236000
0+
#236500
b111 B
1+
#237000
0+
#237500
b1000 B
1+
#238000
0+
#238500
b1001 B
1+
#239000
0+
#239500
b0 B
1+
#240000
0+
0'
#240500
b1 B
1+
#241000
0+
#241500
b10 B
1+
#242000
0+
#242500
b11 B
1+
#243000
0+
#243500
b100 B
1+
#244000
0+
#244500
b101 B
1+
#245000
0+
0(
#245500
b110 B
1+
#246000
0+
#246500
b111 B
1+
#247000
0+
#247500
b1000 B
1+
#248000
0+
#248500
b1001 B
1+
#249000
0+
#249500
0A
b0 B
1+
#250000
0+
#250500
b10001110101001001000101010001010100111000100000 *
b0 $
b0 >
b1 B
1+
#251000
0+
#251500
b10 B
1+
#252000
0+
#252500
b11 B
1+
#253000
0+
#253500
b100 B
1+
#254000
0+
#254500
b101 B
1+
#255000
0+
#255500
b110 B
1+
#256000
0+
#256500
b111 B
1+
#257000
0+
#257500
b1000 B
1+
#258000
0+
#258500
b1001 B
1+
#259000
0+
#259500
0@
b0 B
1+
#260000
0+
1(
#260500
b10100100100010101000100001000000010000000100000 *
b10 $
b10 >
b1 B
1A
1+
#261000
0+
#261500
b10 B
1+
#262000
0+
#262500
b11 B
1+
#263000
0+
#263500
b100 B
1+
#264000
0+
#264500
b101 B
1+
#265000
0+
1'
#265500
b110 B
1+
#266000
0+
#266500
b111 B
1+
#267000
0+
#267500
b1000 B
1+
#268000
0+
#268500
b1001 B
1+
#269000
0+
#269500
b0 B
1+
#270000
0+
0(
#270500
b1 B
1+
#271000
0+
#271500
b10 B
1+
#272000
0+
#272500
b11 B
1+
#273000
0+
#273500
b100 B
1+
#274000
0+
#274500
b101 B
1+
#275000
0+
0'
#275500
b110 B
1+
#276000
0+
#276500
b111 B
1+
#277000
0+
#277500
b1000 B
1+
#278000
0+
#278500
b1001 B
1+
#279000
0+
#279500
0A
b0 B
1+
#280000
0+
#280500
b101 C
b100 ?
b0 D
1#
1%
1+
#281000
0+
#281500
b1 D
1!
1+
#282000
0+
#282500
b10 D
1+
#283000
0+
#283500
b11 D
1+
#284000
0+
#284500
b100 D
1+
#285000
0+
#285500
b110 C
b101 ?
b0 D
1+
#286000
0+
#286500
b10001110101001001000101010001010100111000100000 *
b1 D
0!
b0 $
b0 >
0#
1+
#287000
0+
#287500
b10 D
1+
#288000
0+
#288500
b11 D
1+
#289000
0+
#289500
b100 D
1+
#290000
0+
1(
#290500
b10100100100010101000100001000000010000000100000 *
0%
b10 $
b10 >
b1 B
1A
1+
#291000
0+
#291500
b10 B
1+
#292000
0+
#292500
b11 B
1+
#293000
0+
#293500
b100 B
1+
#294000
0+
#294500
b101 B
1+
#295000
0+
0(
#295500
b110 B
1+
#296000
0+
#296500
b111 B
1+
#297000
0+
#297500
b1000 B
1+
#298000
0+
#298500
b1001 B
1+
#299000
0+
#299500
0A
b0 B
1+
#300000
0+
#300500
b10001110101001001000101010001010100111000100000 *
b101 D
b0 $
b0 >
1%
1+
#301000
0+
#301500
b110 D
1+
#302000
0+
#302500
b111 D
1+
#303000
0+
#303500
b1000 D
1+
#304000
0+
#304500
b1001 D
1+
#305000
0+
#305500
b1010 D
1+
#306000
0+
#306500
b1011 D
1+
#307000
0+
1'
#307500
0%
b1 B
1@
1+
#308000
0+
#308500
b10 B
1+
#309000
0+
#309500
b11 B
1+
#310000
0+
#310500
b100 B
1+
#311000
0+
#311500
b101 B
1+
#312000
0+
0'
#312500
b110 B
1+
#313000
0+
#313500
b111 B
1+
#314000
0+
#314500
b1000 B
1+
#315000
0+
#315500
b1001 B
1+
#316000
0+
#316500
0@
b0 B
1+
#317000
0+
#317500
b1100 D
1%
1+
#318000
0+
#318500
b1101 D
1+
#319000
0+
#319500
b1110 D
1+
#320000
0+
#320500
b1111 D
1+
#321000
0+
#321500
b10000 D
1+
#322000
0+
#322500
b10001 D
1+
#323000
0+
#323500
b10010 D
1+
#324000
0+
#324500
b10011 D
1+
#325000
0+
#325500
b10100 D
1+
#326000
0+
#326500
b10101 D
1+
#327000
0+
#327500
b10110 D
1+
#328000
0+
#328500
b10111 D
1+
#329000
0+
#329500
b11000 D
1+
#330000
0+
#330500
b11001 D
1+
#331000
0+
#331500
b11010 D
1+
#332000
0+
#332500
b11011 D
1+
#333000
0+
#333500
b11100 D
1+
#334000
0+
#334500
b11101 D
1+
#335000
0+
#335500
b1 C
b110 ?
b0 D
1+
#336000
0+
#336500
b10110010100010101001100010011000100111101010111 *
b1 D
b1 $
b1 >
1"
1+
#337000
0+
#337500
b10 D
1+
#338000
0+
#338500
b11 D
1+
#339000
0+
#339500
b100 D
1+
#340000
0+
#340500
b10 C
b1 ?
b0 D
1+
#341000
0+
#341500
b10100100100010101000100001000000010000000100000 *
b10001110101001001000101010001010100111000100000 )
b1 D
b10 $
b10 >
b0 &
b0 =
0"
1#
0%
1+
#342000
0+
#342500
b10 D
1+
#343000
0+
#343500
b11 D
1+
#344000
0+
#344500
b100 D
1+
#345000
0+
#345500
b101 D
1+
#346000
0+
#346500
b110 D
1+
#347000
0+
#347500
b111 D
1+
#348000
0+
#348500
b1000 D
1+
#349000
0+
#349500
b1001 D
1+
#350000
0+
#350500
b1010 D
1+
#351000
0+
#351500
b1011 D
1+
#352000
0+
#352500
b1100 D
1+
#353000
0+
#353500
b1101 D
1+
#354000
0+
#354500
b1110 D
1+
#355000
0+
#355500
b1111 D
1+
#356000
0+
#356500
b10000 D
1+
#357000
0+
#357500
b10001 D
1+
#358000
0+
#358500
b10010 D
1+
#359000
0+
#359500
b10011 D
1+
#360000
0+
#360500
b10100 D
1+
#361000
0+
#361500
b10101 D
1+
#362000
0+
#362500
b10110 D
1+
#363000
0+
#363500
b10111 D
1+
#364000
0+
#364500
b11000 D
1+
#365000
0+
#365500
b11001 D
1+
#366000
0+
#366500
b11010 D
1+
#367000
0+
#367500
b11011 D
1+
#368000
0+
#368500
b11100 D
1+
#369000
0+
#369500
b11101 D
1+
#370000
0+
#370500
b11 C
b10 ?
b0 D
1+
#371000
0+
#371500
b10110010100010101001100010011000100111101010111 )
b1 D
b1 &
b1 =
1+
#372000
0+
#372500
b10 D
1+
#373000
0+
#373500
b11 D
1+
#374000
0+
#374500
b100 D
1+
#375000
0+
#375500
b100 C
b11 ?
b0 D
1+
#376000
0+
#376500
b10100100100010101000100001000000010000000100000 )
b1 D
b10 &
b10 =
1%
1+
