EE1501_DSLab/verilog/assignments/1/main.v
module priority_encoder (
    input [3:0] in,
    output reg [1:0] out,
    output reg valid
);
    always @(*) begin
        valid = | in;
        casez (in)
            4'b1zzz: out = 2'b11;
            4'b01zz: out = 2'b10;
            4'b001z: out = 2'b01;
            4'b0001: out = 2'b00;
            default: out = 2'b00;
        endcase
    end
endmodule

module even_parity_generator(
    input [7:0] data,
    output parity
);
    assign parity = ^ data;
endmodule

module up_counter(
    input clk,
    input reset,
    input enable,
    output reg [3:0] count
);
    always @(posedge clk or posedge reset) begin
        if(reset) count <= 4'b0000;
        else if(enable) begin
            count[0] <= ~count[0];
            if(count[0]) count[1] <= ~count[1]; 
            if(count[0] & count[1]) count[2] <= ~count[2]; 
            if(count[0] & count[1] & count[2]) count[3] <= ~count[3]; 
        end
    end
endmodule

EE1501_DSLab/verilog/assignments/1/tb_akshara.v
`timescale 1ns/1ps

module assignment_1_tb;

  // Inputs for priority_encoder
  reg [3:0] in;
  wire [1:0] out;
  wire valid;

  // Inputs for up_counter
  reg clk;
  reg enable;
  reg reset;
  wire [3:0] count;

  // Inputs for even_parity_generator
  reg [7:0] data;
  wire parity;

  // Instantiate modules
  priority_encoder pe(.in(in), .out(out), .valid(valid));
  up_counter uc(.clk(clk), .count(count), .enable(enable), .reset(reset));
  even_parity_generator epg(.data(data), .parity(parity));

  // Clock generation
  initial begin
    clk = 0;
    forever #5 clk = ~clk;
  end

  // Test stimulus
  initial begin
    // VCD Dump
    $dumpfile("assignment-1.vcd");
    $dumpvars(0, assignment_1_tb);

    // Initialize inputs
    in = 4'b0000;
    enable = 0;
    reset = 1;
    data = 8'h00;

    #10;
    reset = 0;
    enable = 1;

    // Stimuli for priority encoder
    #10 in = 4'b0001;
    #10 in = 4'b0010;
    #10 in = 4'b0100;
    #10 in = 4'b1000;

    // Stimuli for parity generator
    #10 data = 8'b10101010;
    #10 data = 8'b11110000;

    // Let counter run
    #50 enable = 0;

    #50 $finish;
  end

endmodule

EE1501_DSLab/verilog/assignments/1/assignment-1.vcd
$date
	Fri Apr 11 20:41:20 2025
$end
$version
	Icarus Verilog
$end
$timescale
	1ps
$end
$scope module assignment_1_tb $end
$var wire 1 ! valid $end
$var wire 1 " parity $end
$var wire 2 # out [1:0] $end
$var wire 4 $ count [3:0] $end
$var reg 1 % clk $end
$var reg 8 & data [7:0] $end
$var reg 1 ' enable $end
$var reg 4 ( in [3:0] $end
$var reg 1 ) reset $end
$scope module epg $end
$var wire 8 * data [7:0] $end
$var wire 1 " parity $end
$upscope $end
$scope module pe $end
$var wire 4 + in [3:0] $end
$var reg 2 , out [1:0] $end
$var reg 1 ! valid $end
$upscope $end
$scope module uc $end
$var wire 1 % clk $end
$var wire 1 ' enable $end
$var wire 1 ) reset $end
$var reg 4 - count [3:0] $end
$upscope $end
$upscope $end
$enddefinitions $end
$comment Show the parameter values. $end
$dumpall
$end
#0
$dumpvars
b0 -
b0 ,
b0 +
b0 *
1)
b0 (
0'
b0 &
0%
b0 $
b0 #
0"
0!
$end
#5000
1%
#10000
0%
1'
0)
#15000
b1 $
b1 -
1%
#20000
1!
0%
b1 (
b1 +
#25000
b10 $
b10 -
1%
#30000
b1 #
b1 ,
0%
b10 (
b10 +
#35000
b11 $
b11 -
1%
#40000
b10 #
b10 ,
0%
b100 (
b100 +
#45000
b100 $
b100 -
1%
#50000
b11 #
b11 ,
0%
b1000 (
b1000 +
#55000
b101 $
b101 -
1%
#60000
0%
b10101010 &
b10101010 *
#65000
b110 $
b110 -
1%
#70000
0%
b11110000 &
b11110000 *
#75000
b111 $
b111 -
1%
#80000
0%
#85000
b1000 $
b1000 -
1%
#90000
0%
#95000
b1001 $
b1001 -
1%
#100000
0%
#105000
b1010 $
b1010 -
1%
#110000
0%
#115000
b1011 $
b1011 -
1%
#120000
0%
0'
