EE1501_DSLab/verilog/assignments/1/main.v
module priority_encoder (
    input [3:0] in,
    output reg [1:0] out,
    output reg valid
);
    always @(*) begin
        valid = | in;
        casez (in)
            4'b1zzz: out = 2'b11;
            4'b01zz: out = 2'b10;
            4'b001z: out = 2'b01;
            4'b0001: out = 2'b00;
            default: out = 2'b00;
        endcase
    end
endmodule

module even_parity_generator(
    input [7:0] data,
    output parity
);
    assign parity = ^ data;
endmodule

module up_counter(
    input clk,
    input reset,
    input enable,
    output reg [3:0] count
);
    always @(posedge clk or posedge reset) begin
        if(reset) count <= 4'b0000;
        else if(enable) begin
            count[0] <= ~count[0];
            if(count[0]) count[1] <= ~count[1]; 
            if(count[0] & count[1]) count[2] <= ~count[2]; 
            if(count[0] & count[1] & count[2]) count[3] <= ~count[3]; 
        end
    end
endmodule

EE1501_DSLab/verilog/assignments/1/tb_priority_encoder.v
`timescale 1ns / 1ps

module tb_priority_encoder;

    // Inputs
    reg [3:0] in;

    // Outputs
    wire [1:0] out;
    wire valid;

    // Instantiate the Design Under Test (DUT)
    priority_encoder uut (
        .in(in),
        .out(out),
        .valid(valid)
    );

    // VCD generation
    initial begin
        $dumpfile("priority_encoder.vcd");
        $dumpvars(0, tb_priority_encoder);
    end

    // Task to display the output nicely
    task display_outputs;
        begin
            $display("in = %b -> out = %b, valid = %b", in, out, valid);
        end
    endtask

    initial begin
        $display("Starting priority encoder testbench...");
        $monitor("Time %0t: in = %b -> out = %b, valid = %b", $time, in, out, valid);

        // Test all input combinations from 0000 to 1111
        for (integer i = 0; i < 16; i = i + 1) begin
            in = i[3:0];
            #10; // wait 10 time units
        end

        $display("Testbench complete.");
        $finish;
    end

endmodule

EE1501_DSLab/verilog/assignments/1/priority_encoder.vcd
$date
	Wed Apr  9 10:17:08 2025
$end
$version
	Icarus Verilog
$end
$timescale
	1ps
$end
$scope module tb_priority_encoder $end
$var wire 1 ! valid $end
$var wire 2 " out [1:0] $end
$var reg 4 # in [3:0] $end
$scope module uut $end
$var wire 4 $ in [3:0] $end
$var reg 2 % out [1:0] $end
$var reg 1 ! valid $end
$upscope $end
$scope begin $ivl_for_loop0 $end
$var integer 32 & i [31:0] $end
$upscope $end
$scope task display_outputs $end
$upscope $end
$upscope $end
$enddefinitions $end
$comment Show the parameter values. $end
$dumpall
$end
#0
$dumpvars
b0 &
b0 %
b0 $
b0 #
b0 "
0!
$end
#10000
1!
b1 #
b1 $
b1 &
#20000
b1 "
b1 %
b10 #
b10 $
b10 &
#30000
b0 "
b0 %
b11 #
b11 $
b11 &
#40000
b10 "
b10 %
b100 #
b100 $
b100 &
#50000
b0 "
b0 %
b101 #
b101 $
b101 &
#60000
b1 "
b1 %
b110 #
b110 $
b110 &
#70000
b0 "
b0 %
b111 #
b111 $
b111 &
#80000
b11 "
b11 %
b1000 #
b1000 $
b1000 &
#90000
b0 "
b0 %
b1001 #
b1001 $
b1001 &
#100000
b1 "
b1 %
b1010 #
b1010 $
b1010 &
#110000
b0 "
b0 %
b1011 #
b1011 $
b1011 &
#120000
b10 "
b10 %
b1100 #
b1100 $
b1100 &
#130000
b0 "
b0 %
b1101 #
b1101 $
b1101 &
#140000
b1 "
b1 %
b1110 #
b1110 $
b1110 &
#150000
b0 "
b0 %
b1111 #
b1111 $
b1111 &
#160000
b10000 &
