EE1501_DSLab/verilog/assignments/1/main.v
module priority_encoder (
    input [3:0] in,
    output reg [1:0] out,
    output reg valid
);
    always @(*) begin
        valid = | in;
        casez (in)
            4'b1zzz: out = 2'b11;
            4'b01zz: out = 2'b10;
            4'b001z: out = 2'b01;
            4'b0001: out = 2'b00;
            default: out = 2'b00;
        endcase
    end
endmodule

module even_parity_generator(
    input [7:0] data,
    output parity
);
    assign parity = ^ data;
endmodule

module up_counter(
    input clk,
    input reset,
    input enable,
    output reg [3:0] count
);
    always @(posedge clk or posedge reset) begin
        if(reset) count <= 4'b0000;
        else if(enable) begin
            count[0] <= ~count[0];
            if(count[0]) count[1] <= ~count[1]; 
            if(count[0] & count[1]) count[2] <= ~count[2]; 
            if(count[0] & count[1] & count[2]) count[3] <= ~count[3]; 
        end
    end
endmodule

EE1501_DSLab/verilog/assignments/1/tb_up_counter.v
`timescale 1ns/1ps

module tb_up_counter;

    reg clk;
    reg reset;
    reg enable;
    wire [3:0] count;

    // Instantiate DUT
    up_counter dut (
        .clk(clk),
        .reset(reset),
        .enable(enable),
        .count(count)
    );

    // Clock generator: 10ns period
    always #5 clk = ~clk;

    initial begin
        $dumpfile("up_counter.vcd");
        $dumpvars(0, tb_up_counter);

        // Initialize inputs
        clk = 0;
        reset = 1;
        enable = 0;

        // Apply reset
        #10;
        reset = 0;
        enable = 1;

        // Run counter for a while
        #100;

        // Disable counting
        enable = 0;
        #20;

        // Re-enable counting
        enable = 1;
        #70;

        // Reset during operation
        reset = 1;
        #10;
        reset = 0;

        #40;
        $finish;
    end
endmodule

EE1501_DSLab/verilog/assignments/1/up_counter.vcd
$date
	Fri Apr 11 18:44:35 2025
$end
$version
	Icarus Verilog
$end
$timescale
	1ps
$end
$scope module tb_up_counter $end
$var wire 4 ! count [3:0] $end
$var reg 1 " clk $end
$var reg 1 # enable $end
$var reg 1 $ reset $end
$scope module dut $end
$var wire 1 " clk $end
$var wire 1 # enable $end
$var wire 1 $ reset $end
$var reg 4 % count [3:0] $end
$upscope $end
$upscope $end
$enddefinitions $end
$comment Show the parameter values. $end
$dumpall
$end
#0
$dumpvars
b0 %
1$
0#
0"
b0 !
$end
#5000
1"
#10000
0"
1#
0$
#15000
b1 !
b1 %
1"
#20000
0"
#25000
b10 !
b10 %
1"
#30000
0"
#35000
b11 !
b11 %
1"
#40000
0"
#45000
b100 !
b100 %
1"
#50000
0"
#55000
b101 !
b101 %
1"
#60000
0"
#65000
b110 !
b110 %
1"
#70000
0"
#75000
b111 !
b111 %
1"
#80000
0"
#85000
b1000 !
b1000 %
1"
#90000
0"
#95000
b1001 !
b1001 %
1"
#100000
0"
#105000
b1010 !
b1010 %
1"
#110000
0"
0#
#115000
1"
#120000
0"
#125000
1"
#130000
0"
1#
#135000
b1011 !
b1011 %
1"
#140000
0"
#145000
b1100 !
b1100 %
1"
#150000
0"
#155000
b1101 !
b1101 %
1"
#160000
0"
#165000
b1110 !
b1110 %
1"
#170000
0"
#175000
b1111 !
b1111 %
1"
#180000
0"
#185000
b0 !
b0 %
1"
#190000
0"
#195000
b1 !
b1 %
1"
#200000
b0 !
b0 %
0"
1$
#205000
1"
#210000
0"
0$
#215000
b1 !
b1 %
1"
#220000
0"
#225000
b10 !
b10 %
1"
#230000
0"
#235000
b11 !
b11 %
1"
#240000
0"
#245000
b100 !
b100 %
1"
