EE1501_DSLab/verilog/assignments/2/ripple_adder_nand/ripple_adder_nand.v
`timescale 1ns/1ns

module ripple_adder_nand (
    input [3:0] a,
    input [3:0] b,
    input cin,
    output [3:0] sum,
    output cout
);
    wire cout1, cout2, cout3;
    full_adder_nand adder1(.a(a[0]), .b(b[0]), .cin(cin), .sum(sum[0]), .cout(cout1));
    full_adder_nand adder2(.a(a[1]), .b(b[1]), .cin(cout1), .sum(sum[1]), .cout(cout2));
    full_adder_nand adder3(.a(a[2]), .b(b[2]), .cin(cout2), .sum(sum[2]), .cout(cout3));
    full_adder_nand adder4(.a(a[3]), .b(b[3]), .cin(cout3), .sum(sum[3]), .cout(cout));
endmodule

module full_adder_nand (
    input a,
    input b,
    input cin,
    output sum,
    output cout
);

    // sum = a ^ b ^ cin;
    wire ab_xor;

    xor_nand xor_gate1(a, b, ab_xor);
    xor_nand xor_gate2(ab_xor, cin, sum);

    // carry (cout) = a & b | cin & a | cin & b;
    wire and1, and2, and3, or1;

    and_nand and_gate1(a, b, and1);
    and_nand and_gate2(cin, a, and2);
    and_nand and_gate3(cin, b, and3);
    or_nand or_gate1(and1, and2, or1);
    or_nand or_gate2(and3, or1, cout);
endmodule

module xor_nand (
    input a,
    input b,
    output out
);
    wire ab_nand, a_ab_nand, b_ab_nand;
    nand #1(ab_nand, a, b);
    nand #1(a_ab_nand, ab_nand, a);
    nand #1(b_ab_nand, ab_nand, b);
    nand #1(out, a_ab_nand, b_ab_nand);
endmodule

module and_nand (
    input a,
    input b,
    output out
);
    wire ab_nand;
    nand #1(ab_nand, a, b);
    nand #1(out, ab_nand, ab_nand); // basically not of nand
endmodule

module or_nand (
    input a,
    input b,
    output out
);
    wire ab_nand, a_not, b_not;
    nand #1(a_not, a, a); // not gate
    nand #1(b_not, b, b); // not gate
    nand #1(out, a_not, b_not);
endmodule

EE1501_DSLab/verilog/assignments/2/ripple_adder_nand/tb_ripple_adder_nand.v
`timescale 1ns/1ns

module tb_ripple_adder_nand;
    reg [3:0] a;
    reg [3:0] b;
    reg cin;
    wire [3:0] sum;
    wire cout;

    ripple_adder_nand dut(.a(a), .b(b), .cin(cin), .sum(sum), .cout(cout));

    initial begin
        $dumpfile("ripple_adder_nand.vcd");
        $dumpvars(0, tb_ripple_adder_nand);
        //$monitor("\na = %b, b = %b, cin = %b\nsum = %b, cout = %b", a, b, cin, sum, cout);

        a = 4'b0000; b = 4'b0000; cin = 1'b0;
        #50 a = 4'b1111; b = 4'b0000; cin = 1'b1;
        #50 a = 4'b1010; b = 4'b0101; cin = 1'b1;
        #50 a = 4'b1111; b = 4'b0001; cin = 1'b0;
        #50 a = 4'b1000; b = 4'b0001; cin = 1'b0;
        #50;
        /*
        #50 a = 4'b1111; b = 4'b1111; cin = 1'b0;
        #50 a = 4'b1010; b = 4'b0101; cin = 1'b0;
        #50 a = 4'b0001; b = 4'b0001; cin = 1'b1;
        #50 a = 4'b0110; b = 4'b1001; cin = 1'b0;
        #50 a = 4'b1111; b = 4'b1111; cin = 1'b1;
        #50 a = 4'b0000; b = 4'b1010; cin = 1'b0;
        #50 a = 4'b1111; b = 4'b0000; cin = 1'b0;
        #50 a = 4'b1001; b = 4'b1001; cin = 1'b0;
        #50 a = 4'b0111; b = 4'b0001; cin = 1'b1;
        */

        $finish;
    end
endmodule

/*
module tb_ripple_adder_nand;
    reg [3:0] a;
    reg [3:0] b;
    reg cin;
    wire [3:0] sum;
    wire cout;

    ripple_adder_nand dut(.a(a), .b(b), .cin(cin), .sum(sum), .cout(cout));
    integer i, j, k, l, m, n, expected_sum;
    integer a_happen, b_happen, cin_happen;
    integer a_happen2, b_happen2, cin_happen2;
    integer cur_time, max_time;

    initial begin
        //$dumpfile("ripple_adder_nand.vcd");
        //$dumpvars(0, tb_ripple_adder_nand);
        //$monitor("\na = %b, b = %b, cin = %b\nsum = %b, cout = %b", a, b, cin, sum, cout);
        max_time = 0;
        for(i = 0; i < 16; i++) begin
            for(j = 0; j < 16; j++) begin
                for(k = 0; k < 16; k++) begin
                    for(l = 0; l < 16; l++) begin
                        for(m = 0; m < 2; m++) begin
                            for(n = 0; n < 2; n++) begin
                                a = i[3:0];
                                b = j[3:0];
                                cin = m[0];
                                #50;

                                cur_time = $time;
                                a = k[3:0];
                                b = l[3:0];
                                cin = n[0];

                                expected_sum = a + b + cin;
                                wait(sum == expected_sum[3:0] && cout == expected_sum[4]);

                                if($time - cur_time > max_time) begin
                                    a_happen = k;
                                    b_happen = l;
                                    cin_happen = n;

                                    a_happen2 = i;
                                    b_happen2 = j;
                                    cin_happen2 = m;
                                    $display("%0d, %0d", $time - cur_time, max_time);
                                    max_time = $time - cur_time;
                                end
                                //$display("%0d", $time - cur_time);
                            end
                        end
                    end
                end
            end
        end

        $display("%0d ns, %0d, %0d, %0d -> %0d, %0d, %0d", max_time, a_happen2, b_happen2, cin_happen2, a_happen, b_happen, cin_happen);
        $finish;
    end
endmodule
*/

EE1501_DSLab/verilog/assignments/2/ripple_adder_nand/ripple_adder_nand.vcd
$date
	Tue Apr 22 23:42:59 2025
$end
$version
	Icarus Verilog
$end
$timescale
	1ns
$end
$scope module tb_ripple_adder_nand $end
$var wire 4 ! sum [3:0] $end
$var wire 1 " cout $end
$var reg 4 # a [3:0] $end
$var reg 4 $ b [3:0] $end
$var reg 1 % cin $end
$scope module dut $end
$var wire 4 & a [3:0] $end
$var wire 4 ' b [3:0] $end
$var wire 1 % cin $end
$var wire 4 ( sum [3:0] $end
$var wire 1 ) cout3 $end
$var wire 1 * cout2 $end
$var wire 1 + cout1 $end
$var wire 1 " cout $end
$scope module adder1 $end
$var wire 1 , a $end
$var wire 1 - b $end
$var wire 1 % cin $end
$var wire 1 . sum $end
$var wire 1 / or1 $end
$var wire 1 + cout $end
$var wire 1 0 and3 $end
$var wire 1 1 and2 $end
$var wire 1 2 and1 $end
$var wire 1 3 ab_xor $end
$scope module and_gate1 $end
$var wire 1 , a $end
$var wire 1 4 ab_nand $end
$var wire 1 - b $end
$var wire 1 2 out $end
$upscope $end
$scope module and_gate2 $end
$var wire 1 % a $end
$var wire 1 5 ab_nand $end
$var wire 1 , b $end
$var wire 1 1 out $end
$upscope $end
$scope module and_gate3 $end
$var wire 1 % a $end
$var wire 1 6 ab_nand $end
$var wire 1 - b $end
$var wire 1 0 out $end
$upscope $end
$scope module or_gate1 $end
$var wire 1 2 a $end
$var wire 1 7 a_not $end
$var wire 1 1 b $end
$var wire 1 8 b_not $end
$var wire 1 / out $end
$upscope $end
$scope module or_gate2 $end
$var wire 1 0 a $end
$var wire 1 9 a_not $end
$var wire 1 / b $end
$var wire 1 : b_not $end
$var wire 1 + out $end
$upscope $end
$scope module xor_gate1 $end
$var wire 1 , a $end
$var wire 1 ; a_ab_nand $end
$var wire 1 < ab_nand $end
$var wire 1 - b $end
$var wire 1 = b_ab_nand $end
$var wire 1 3 out $end
$upscope $end
$scope module xor_gate2 $end
$var wire 1 3 a $end
$var wire 1 > a_ab_nand $end
$var wire 1 ? ab_nand $end
$var wire 1 % b $end
$var wire 1 @ b_ab_nand $end
$var wire 1 . out $end
$upscope $end
$upscope $end
$scope module adder2 $end
$var wire 1 A a $end
$var wire 1 B b $end
$var wire 1 + cin $end
$var wire 1 C sum $end
$var wire 1 D or1 $end
$var wire 1 * cout $end
$var wire 1 E and3 $end
$var wire 1 F and2 $end
$var wire 1 G and1 $end
$var wire 1 H ab_xor $end
$scope module and_gate1 $end
$var wire 1 A a $end
$var wire 1 I ab_nand $end
$var wire 1 B b $end
$var wire 1 G out $end
$upscope $end
$scope module and_gate2 $end
$var wire 1 + a $end
$var wire 1 J ab_nand $end
$var wire 1 A b $end
$var wire 1 F out $end
$upscope $end
$scope module and_gate3 $end
$var wire 1 + a $end
$var wire 1 K ab_nand $end
$var wire 1 B b $end
$var wire 1 E out $end
$upscope $end
$scope module or_gate1 $end
$var wire 1 G a $end
$var wire 1 L a_not $end
$var wire 1 F b $end
$var wire 1 M b_not $end
$var wire 1 D out $end
$upscope $end
$scope module or_gate2 $end
$var wire 1 E a $end
$var wire 1 N a_not $end
$var wire 1 D b $end
$var wire 1 O b_not $end
$var wire 1 * out $end
$upscope $end
$scope module xor_gate1 $end
$var wire 1 A a $end
$var wire 1 P a_ab_nand $end
$var wire 1 Q ab_nand $end
$var wire 1 B b $end
$var wire 1 R b_ab_nand $end
$var wire 1 H out $end
$upscope $end
$scope module xor_gate2 $end
$var wire 1 H a $end
$var wire 1 S a_ab_nand $end
$var wire 1 T ab_nand $end
$var wire 1 + b $end
$var wire 1 U b_ab_nand $end
$var wire 1 C out $end
$upscope $end
$upscope $end
$scope module adder3 $end
$var wire 1 V a $end
$var wire 1 W b $end
$var wire 1 * cin $end
$var wire 1 X sum $end
$var wire 1 Y or1 $end
$var wire 1 ) cout $end
$var wire 1 Z and3 $end
$var wire 1 [ and2 $end
$var wire 1 \ and1 $end
$var wire 1 ] ab_xor $end
$scope module and_gate1 $end
$var wire 1 V a $end
$var wire 1 ^ ab_nand $end
$var wire 1 W b $end
$var wire 1 \ out $end
$upscope $end
$scope module and_gate2 $end
$var wire 1 * a $end
$var wire 1 _ ab_nand $end
$var wire 1 V b $end
$var wire 1 [ out $end
$upscope $end
$scope module and_gate3 $end
$var wire 1 * a $end
$var wire 1 ` ab_nand $end
$var wire 1 W b $end
$var wire 1 Z out $end
$upscope $end
$scope module or_gate1 $end
$var wire 1 \ a $end
$var wire 1 a a_not $end
$var wire 1 [ b $end
$var wire 1 b b_not $end
$var wire 1 Y out $end
$upscope $end
$scope module or_gate2 $end
$var wire 1 Z a $end
$var wire 1 c a_not $end
$var wire 1 Y b $end
$var wire 1 d b_not $end
$var wire 1 ) out $end
$upscope $end
$scope module xor_gate1 $end
$var wire 1 V a $end
$var wire 1 e a_ab_nand $end
$var wire 1 f ab_nand $end
$var wire 1 W b $end
$var wire 1 g b_ab_nand $end
$var wire 1 ] out $end
$upscope $end
$scope module xor_gate2 $end
$var wire 1 ] a $end
$var wire 1 h a_ab_nand $end
$var wire 1 i ab_nand $end
$var wire 1 * b $end
$var wire 1 j b_ab_nand $end
$var wire 1 X out $end
$upscope $end
$upscope $end
$scope module adder4 $end
$var wire 1 k a $end
$var wire 1 l b $end
$var wire 1 ) cin $end
$var wire 1 m sum $end
$var wire 1 n or1 $end
$var wire 1 " cout $end
$var wire 1 o and3 $end
$var wire 1 p and2 $end
$var wire 1 q and1 $end
$var wire 1 r ab_xor $end
$scope module and_gate1 $end
$var wire 1 k a $end
$var wire 1 s ab_nand $end
$var wire 1 l b $end
$var wire 1 q out $end
$upscope $end
$scope module and_gate2 $end
$var wire 1 ) a $end
$var wire 1 t ab_nand $end
$var wire 1 k b $end
$var wire 1 p out $end
$upscope $end
$scope module and_gate3 $end
$var wire 1 ) a $end
$var wire 1 u ab_nand $end
$var wire 1 l b $end
$var wire 1 o out $end
$upscope $end
$scope module or_gate1 $end
$var wire 1 q a $end
$var wire 1 v a_not $end
$var wire 1 p b $end
$var wire 1 w b_not $end
$var wire 1 n out $end
$upscope $end
$scope module or_gate2 $end
$var wire 1 o a $end
$var wire 1 x a_not $end
$var wire 1 n b $end
$var wire 1 y b_not $end
$var wire 1 " out $end
$upscope $end
$scope module xor_gate1 $end
$var wire 1 k a $end
$var wire 1 z a_ab_nand $end
$var wire 1 { ab_nand $end
$var wire 1 l b $end
$var wire 1 | b_ab_nand $end
$var wire 1 r out $end
$upscope $end
$scope module xor_gate2 $end
$var wire 1 r a $end
$var wire 1 } a_ab_nand $end
$var wire 1 ~ ab_nand $end
$var wire 1 ) b $end
$var wire 1 !" b_ab_nand $end
$var wire 1 m out $end
$upscope $end
$upscope $end
$upscope $end
$upscope $end
$enddefinitions $end
$comment Show the parameter values. $end
$dumpall
$end
#0
$dumpvars
x!"
x~
x}
x|
x{
xz
xy
xx
xw
xv
xu
xt
xs
xr
xq
xp
xo
xn
xm
0l
0k
xj
xi
xh
xg
xf
xe
xd
xc
xb
xa
x`
x_
x^
x]
x\
x[
xZ
xY
xX
0W
0V
xU
xT
xS
xR
xQ
xP
xO
xN
xM
xL
xK
xJ
xI
xH
xG
xF
xE
xD
xC
0B
0A
x@
x?
x>
x=
x<
x;
x:
x9
x8
x7
x6
x5
x4
x3
x2
x1
x0
x/
x.
0-
0,
x+
x*
x)
bx (
b0 '
b0 &
0%
b0 $
b0 #
x"
bx !
$end
#1
1=
1K
1R
1`
1g
1u
1|
14
1<
1;
1I
1J
1Q
1P
1^
1_
1f
1e
1s
1t
1{
1z
1@
1?
16
15
#2
0E
0Z
0o
02
03
0G
0F
0H
0\
0[
0]
0q
0p
0r
00
01
#3
1N
1c
1x
17
1>
1L
1M
1T
1S
1a
1b
1i
1h
1v
1w
1~
1}
19
18
#4
bx0 !
bx0 (
0.
0D
0Y
0n
0/
#5
1O
1d
1y
1:
#6
0*
0)
0"
0+
#7
1j
1!"
1U
#8
0X
0m
b0 !
b0 (
0C
#50
1,
1A
1V
1k
1%
b1111 #
b1111 &
#51
0;
0P
0e
0z
05
0@
#52
13
1H
1]
1r
11
b1 !
b1 (
1.
#53
0?
0>
0S
0h
0}
08
#54
1>
1@
1C
1X
b1111 !
b1111 (
1m
1/
#55
b1110 !
b1110 (
0.
0:
#56
1+
#57
0J
0T
0U
#58
1F
1S
1U
#59
0M
b1100 !
b1100 (
0C
#60
1D
#61
0O
#62
1*
#63
0_
0i
0j
#64
1[
1h
1j
#65
0b
b1000 !
b1000 (
0X
#66
1Y
#67
0d
#68
1)
#69
0t
0~
0!"
#70
1p
1}
1!"
#71
0w
b0 !
b0 (
0m
#72
1n
#73
0y
#74
1"
#100
1-
1W
0,
0V
b101 $
b101 '
b1010 #
b1010 &
#101
06
0=
0`
0g
15
1;
1_
1e
#102
10
1Z
01
0[
#103
09
0c
18
1b
#104
0/
0Y
#105
1:
1d
#150
0W
1,
1V
0%
b1 $
b1 '
b1111 #
b1111 &
#151
1`
1g
04
0<
0;
0_
0e
16
1?
#152
0Z
12
1;
1=
1[
00
0>
#153
1c
07
03
0b
19
b1 !
b1 (
1.
#154
0)
1/
1>
1Y
0+
#155
1t
1~
0:
b0 !
b0 (
0.
0d
1J
1T
#156
0p
0}
1+
1)
0F
0S
#157
1w
1m
0J
0T
0U
0t
0~
0!"
1M
b1010 !
b1010 (
1C
#158
0n
1F
1S
1U
1p
1}
1!"
0D
#159
1y
0M
0C
0w
b0 !
b0 (
0m
1O
#160
0"
1D
1n
0*
#161
0O
0y
1_
1i
#162
1*
1"
0[
0h
#163
0_
0i
0j
1b
b100 !
b100 (
1X
#164
1[
1h
1j
0Y
#165
0b
b0 !
b0 (
0X
1d
#166
1Y
0)
#167
0d
1t
1~
#168
1)
0p
0}
#169
0t
0~
0!"
1w
b1000 !
b1000 (
1m
#170
1p
1}
1!"
0n
#171
0w
b0 !
b0 (
0m
1y
#172
1n
0"
#173
0y
#174
1"
#200
0,
0A
0V
b1000 #
b1000 &
#201
14
1<
1J
1P
1_
1e
#202
02
0=
0F
0H
0[
0]
#203
17
13
1M
1T
1b
1i
#204
0/
0>
0D
0U
0Y
0j
#205
1:
1.
1O
1C
1d
b111 !
b111 (
1X
#206
0+
0*
0)
#207
1U
1j
1t
1~
#208
0C
b1 !
b1 (
0X
0p
0}
#209
1w
b1001 !
b1001 (
1m
#210
0n
#211
1y
#212
0"
