EE1501_DSLab/project/main.v
module clock_handler (
    input clk,
    input reset,
    input set_time,
    input [7:0] input_sec,
    input [7:0] input_min,
    input [7:0] input_hour,

    output reg [7:0] current_24_sec,
    output reg [7:0] current_24_min,
    output reg [7:0] current_24_hour
);

// synchronous time set and update
always @(posedge clk or posedge reset) begin
    if (reset) begin
        current_24_sec  <= 0;
        current_24_min  <= 0;
        current_24_hour <= 0;
    end else if (set_time == 1'd1) begin
        current_24_sec  <= input_sec;
        current_24_min  <= input_min;
        current_24_hour <= input_hour;
    end else begin
        if (current_24_sec == 8'd59) begin
            current_24_sec <= 8'd0;
            if (current_24_min == 8'd59) begin
                current_24_min <= 8'd0;
                if (current_24_hour == 8'd23) begin
                    current_24_hour <= 8'd0;
                end else begin
                    current_24_hour <= current_24_hour + 1;
                end
            end else begin
                current_24_min <= current_24_min + 1;
            end
        end else begin
            current_24_sec <= current_24_sec + 1;
        end
    end
end

endmodule

module display_handler (
    input clk,
    input hour_format, // 1 for 12 hour, 0 for 24 hour format
    input timer_running,

    input [7:0] current_24_sec,
    input [7:0] current_24_min,
    input [7:0] current_24_hour,

    input [7:0] timer_min,
    input [7:0] timer_sec,

    output reg [7:0] display_sec,
    output reg [7:0] display_min,
    output reg [7:0] display_hour,
    output reg is_pm
);

// Display time in 12-hour or 24-hour format
always @(posedge clk) begin
    if(timer_running) begin
        display_sec <= timer_sec;
        display_min <= timer_min;
        display_hour <= 8'd0;

    end else begin
        display_sec <= current_24_sec;
        display_min <= current_24_min;

        if (hour_format == 1'b1) begin  // 12-hour format
            if (current_24_hour == 0) begin
                display_hour <= 8'd12;  // 12 AM (midnight)
            end else if (current_24_hour == 12) begin
                display_hour <= 8'd12;  // 12 PM (noon)
            end else if (current_24_hour > 12) begin
                display_hour <= current_24_hour - 12;  // PM hours
            end else begin
                display_hour <= current_24_hour;  // AM hours
            end
        end else begin  // 24-hour format
            display_hour <= current_24_hour;
        end

        if (hour_format == 1'b1) begin  // 12-hour format
            is_pm <= (current_24_hour >= 12) ? 1'b1 : 1'b0;
        end else begin
            is_pm <= 1'b0;  // Don't care in 24-hour mode
        end
    end
end

endmodule

module date_handler (
    input clk,
    input reset,
    input set_date,
    input [7:0] input_day,
    input [7:0] input_month,
    input [15:0] input_year,

    // Clock time inputs to detect day changes
    input [7:0] current_24_hour,
    input [7:0] current_24_min,
    input [7:0] current_24_sec,

    // Date outputs
    output reg [ 7:0] current_day,
    output reg [ 7:0] current_month,
    output reg [15:0] current_year
);

// Internal signals
reg [7:0] days_in_current_month;

// Date handling logic
always @(posedge clk or posedge reset) begin
    if (reset) begin
        // Reset to default date
        current_day   <= 8'd1;
        current_month <= 8'd1;
        current_year  <= 16'd2020;

    end else if (set_date) begin
        // Set date manually when set_date is active
        current_day   <= input_day;
        current_month <= input_month;
        current_year  <= input_year;

    end else if (current_24_hour == 8'd23 && current_24_min == 8'd59 && current_24_sec == 8'd59) begin
        // Day changes at midnight (23:59:59)

        // First determine days in current month without using a function
        case (current_month)
            8'd1, 8'd3, 8'd5, 8'd7, 8'd8, 8'd10, 8'd12:
                days_in_current_month = 8'd31;  // Jan, Mar, May, Jul, Aug, Oct, Dec

            8'd4, 8'd6, 8'd9, 8'd11: days_in_current_month = 8'd30;  // Apr, Jun, Sep, Nov

            8'd2: begin  // February
                // Check leap year
                if (((current_year % 4 == 0) && (current_year % 100 != 0)) || (current_year % 400 == 0))
                    days_in_current_month = 8'd29;  // Leap year
                else days_in_current_month = 8'd28;  // Non-leap year
            end

            default: days_in_current_month = 8'd30;  // Default case
        endcase

        // Update date
        if (current_day == days_in_current_month) begin
            current_day <= 8'd1;  // Reset day to 1

            if (current_month == 8'd12) begin
                current_month <= 8'd1;  // Reset month to January
                current_year  <= current_year + 16'd1;  // Increment year
            end else begin
                current_month <= current_month + 8'd1;  // Increment month
            end
        end else begin
            current_day <= current_day + 8'd1;  // Increment day
        end
    end
end

endmodule

module alarm_handler (
    input clk,
    input set_alarm,

    input [7:0] current_24_sec,
    input [7:0] current_24_min,
    input [7:0] current_24_hour,

    input [7:0] alarm_input_sec,
    input [7:0] alarm_input_min,
    input [7:0] alarm_input_hour,

    input snooze_alarm,
    input stop_alarm,

    output reg alarm_buzzer
);
    reg [7:0] input_sec_internal;
    reg [7:0] input_min_internal;
    reg [7:0] input_hour_internal;
    reg [9:0] counter;
    reg is_snoozed;
    reg is_buzzing;

always @(posedge clk) begin
    // Stop alarm functionality
    if(stop_alarm) begin
        is_buzzing <= 0;
        alarm_buzzer <= 0;
        counter <= 0;
    end
    // Snooze alarm functionality
    else if(snooze_alarm) begin
        is_snoozed <= 1;
        alarm_buzzer <= 0;
        is_buzzing <= 0;
        counter <= 0;
    end
    // Set alarm functionality
    else if(set_alarm) begin
        input_sec_internal <= alarm_input_sec;
        input_min_internal <= alarm_input_min;
        input_hour_internal <= alarm_input_hour;
        is_snoozed <= 0;
        alarm_buzzer <= 0;
        is_buzzing <= 0;
        counter <= 0;
    end
    // Snooze timer functionality
    else if(is_snoozed) begin
        alarm_buzzer <= 0;
        is_buzzing <= 0;
        counter <= counter + 1;
        if(counter >= 5) begin  // After snooze period (300 clock cycles)
            is_snoozed <= 0;
            alarm_buzzer <= 1;
            is_buzzing <= 1;
            counter <= 0;
        end
    end
    // Alarm matching current time
    else if ((input_sec_internal == current_24_sec &&
              input_min_internal == current_24_min &&
              input_hour_internal == current_24_hour) || is_buzzing) begin
        if(!is_buzzing) is_buzzing <= 1;
        alarm_buzzer <= 1;
    end
    // Default state - alarm not active
    else begin
        alarm_buzzer <= 0;
    end
end

endmodule

module timer_handler (
    input clk,
    input reset,
    input start_timer,
    input stop_timer,
    input set_timer,
    input [7:0] input_min,
    input [7:0] input_sec,

    output reg [7:0] timer_min,
    output reg [7:0] timer_sec,
    output reg timer_running,
    output reg timer_buzzer
);

reg [7:0] max_min = 8'd10;

always @(posedge clk or posedge reset) begin
    if (reset) begin
        timer_min <= 8'd0;
        timer_sec <= 8'd0;
        timer_running <= 1'b0;
        timer_buzzer <= 1'b0;
    end else if (set_timer) begin
        if (input_min > max_min) begin
            // Limit to maximum 10 minutes
            timer_min <= max_min;
            timer_sec <= input_sec;
        end else begin
            timer_min <= input_min;
            timer_sec <= input_sec;
        end
        timer_running <= 1'b0;
        timer_buzzer <= 1'b0;
    end else if (start_timer) begin
        timer_running <= 1'b1;
        timer_buzzer <= 1'b0;
    end else if (stop_timer) begin
        // Stop the timer
        timer_running <= 1'b0;
        timer_buzzer <= 1'b0;
    end

    if (timer_running) begin
        // Timer is running, decrement
        if (timer_sec == 8'd0) begin
            if (timer_min == 8'd0) begin
                // Timer has reached zero
                timer_running <= 1'b0;
                timer_buzzer <= 1'b1;
            end else begin
                // Decrement minute, reset seconds to 59
                timer_min <= timer_min - 8'd1;
                timer_sec <= 8'd59;
            end
        end else begin
            // Decrement seconds
            timer_sec <= timer_sec - 8'd1;
        end
    end
end

endmodule

module main_driver (
    input        clk,
    input        reset,
    input        hour_format,
    input        set_time,
    input        set_date,
    input        set_alarm,
    input        snooze_alarm,
    input        stop_alarm,
    input        set_timer,
    input        start_timer,
    input        stop_timer,

    input  [7:0] input_sec,
    input  [7:0] input_min,
    input  [7:0] input_hour,
    input  [7:0] input_day,
    input  [7:0] input_month,
    input [15:0] input_year,
    input  [7:0] timer_input_min,
    input  [7:0] timer_input_sec,
    input  [7:0] alarm_input_sec,
    input  [7:0] alarm_input_min,
    input  [7:0] alarm_input_hour,

    output [7:0] current_24_sec,
    output [7:0] current_24_min,
    output [7:0] current_24_hour,
    output [7:0] display_sec,
    output [7:0] display_min,
    output [7:0] display_hour,
    output [7:0] current_day,
    output [7:0] current_month,
    output [15:0] current_year,
    output [7:0] timer_min,
    output [7:0] timer_sec,
    output       timer_running,
    output       timer_buzzer,
    output       alarm_buzzer,
    output       is_pm
);
    // Instantiate the clock_handler module
    clock_handler clock_module (
        .clk(clk),
        .reset(reset),
        .set_time(set_time),
        .input_sec(input_sec),
        .input_min(input_min),
        .input_hour(input_hour),
        .current_24_sec(current_24_sec),
        .current_24_min(current_24_min),
        .current_24_hour(current_24_hour)
    );

    // Instantiate the display_handler module
    display_handler display_module (
        .clk(clk),
        .hour_format(hour_format),
        .current_24_sec(current_24_sec),
        .current_24_min(current_24_min),
        .current_24_hour(current_24_hour),
        .timer_min(timer_min),
        .timer_sec(timer_sec),
        .timer_running(timer_running),
        .display_sec(display_sec),
        .display_min(display_min),
        .display_hour(display_hour),
        .is_pm(is_pm)
    );

    // Instantiate the date_handler module
    date_handler date_module (
        .clk(clk),
        .reset(reset),
        .set_date(set_date),
        .input_day(input_day),
        .input_month(input_month),
        .input_year(input_year),
        .current_24_hour(current_24_hour),
        .current_24_min(current_24_min),
        .current_24_sec(current_24_sec),
        .current_day(current_day),
        .current_month(current_month),
        .current_year(current_year)
    );

    // Instantiate the timer_handler module
    timer_handler timer_module (
        .clk(clk),
        .reset(reset),
        .set_timer(set_timer),
        .start_timer(start_timer),
        .stop_timer(stop_timer),
        .input_min(timer_input_min),
        .input_sec(timer_input_sec),
        .timer_min(timer_min),
        .timer_sec(timer_sec),
        .timer_running(timer_running),
        .timer_buzzer(timer_buzzer)
    );

    // Instantiate the alarm_handler module
    alarm_handler alarm_module (
        .clk(clk),
        .set_alarm(set_alarm),
        .snooze_alarm(snooze_alarm),
        .stop_alarm(stop_alarm),
        .current_24_hour(current_24_hour),
        .current_24_min(current_24_min),
        .current_24_sec(current_24_sec),
        .alarm_input_sec(alarm_input_sec),
        .alarm_input_min(alarm_input_min),
        .alarm_input_hour(alarm_input_hour),
        .alarm_buzzer(alarm_buzzer)
    );
endmodule

EE1501_DSLab/project/final/digital_clock/main_tb2.v
`timescale 1s/1ms

module clock_tb;
    // Inputs
    reg clk;
    reg reset;
    reg hour_format;
    reg set_time;
    reg set_date;
    reg set_alarm;
    reg snooze_alarm;
    reg stop_alarm;
    reg set_timer;
    reg start_timer;
    reg stop_timer;
    
    reg [7:0] input_sec;
    reg [7:0] input_min;
    reg [7:0] input_hour;
    reg [7:0] input_day;
    reg [7:0] input_month;
    reg [15:0] input_year;
    reg [7:0] timer_input_min;
    reg [7:0] timer_input_sec;
    reg [7:0] alarm_input_sec;
    reg [7:0] alarm_input_min;
    reg [7:0] alarm_input_hour;
    
    // Outputs
    wire [7:0] current_24_sec;
    wire [7:0] current_24_min;
    wire [7:0] current_24_hour;
    wire [7:0] display_sec;
    wire [7:0] display_min;
    wire [7:0] display_hour;
    wire [7:0] current_day;
    wire [7:0] current_month;
    wire [15:0] current_year;
    wire [7:0] timer_min;
    wire [7:0] timer_sec;
    wire timer_running;
    wire timer_buzzer;
    wire alarm_buzzer;
    
    // Instantiating the main driver for the clock
    main_driver dut (
        .clk(clk),
        .reset(reset),
        .hour_format(hour_format),
        .set_time(set_time),
        .set_date(set_date),
        .set_alarm(set_alarm),
        .snooze_alarm(snooze_alarm),
        .stop_alarm(stop_alarm),
        .set_timer(set_timer),
        .start_timer(start_timer),
        .stop_timer(stop_timer),
        .input_sec(input_sec),
        .input_min(input_min),
        .input_hour(input_hour),
        .input_day(input_day),
        .input_month(input_month),
        .input_year(input_year),
        .timer_input_min(timer_input_min),
        .timer_input_sec(timer_input_sec),
        .alarm_input_sec(alarm_input_sec),
        .alarm_input_min(alarm_input_min),
        .alarm_input_hour(alarm_input_hour),
        .current_24_sec(current_24_sec),
        .current_24_min(current_24_min),
        .current_24_hour(current_24_hour),
        .display_sec(display_sec),
        .display_min(display_min),
        .display_hour(display_hour),
        .current_day(current_day),
        .current_month(current_month),
        .current_year(current_year),
        .timer_min(timer_min),
        .timer_sec(timer_sec),
        .timer_running(timer_running),
        .timer_buzzer(timer_buzzer),
        .alarm_buzzer(alarm_buzzer)
    );
    
    // AM/PM indicator logic
    reg is_pm;
    reg [15:0] am_pm_indicator;
    
    // Display logic for AM/PM indicator
    always @(*) begin
        is_pm = (current_24_hour >= 8'd12);
        
        if (hour_format) begin
            if (is_pm)
                am_pm_indicator = {"P", "M"};  // 'P' = 8'h50, 'M' = 8'h4D
            else
                am_pm_indicator = {"A", "M"};  // 'A' = 8'h41, 'M' = 8'h4D
        end else begin
            am_pm_indicator = "  ";  // Two spaces if 24-hour
        end
    end
    
    // Clock generation (1 Hz clock for seconds)
    initial begin
        clk = 0;
        forever #0.5 clk = ~clk;  // 1 second period
    end
    
    // Test sequence
    initial begin
        // Initialize all inputs
        reset = 0;
        hour_format = 0;  // 24-hour mode
        set_time = 0;
        set_date = 0;
        set_alarm = 0;
        snooze_alarm = 0;
        stop_alarm = 0;
        set_timer = 0;
        start_timer = 0;
        stop_timer = 0;
        
        input_sec = 0;
        input_min = 0;
        input_hour = 0;
        input_day = 0;
        input_month = 0;
        input_year = 0;
        timer_input_min = 0;
        timer_input_sec = 0;
        alarm_input_sec = 0;
        alarm_input_min = 0;
        alarm_input_hour = 0;
        
        // First reset
        #1 reset = 1;
        #2 reset = 0;
        $display("Reset done at %0ds", $time);
        
        // Set date to Dec 31 2022, time to 23:53:55
        input_day = 8'd31;
        input_month = 8'd12;
        input_year = 16'd2022;
        #1 set_date = 1;
        #1 set_date = 0;
        
        input_hour = 8'd23;
        input_min = 8'd59;
        input_sec = 8'd58;
        #1 set_time = 1;
        $display("Set date to Dec 31 2022, time to 23:59:58 at %0ds", $time);
        #1 set_time = 0;
        
        $display("Waiting for next day to start...");
        #2;
        $display("Next day started at %0ds", $time);
        
        // Change to AM-PM mode
        #1 hour_format = 1;
        $display("Changed to AM-PM mode at %0ds", $time);
        
        // Wait for 10 seconds
        #10;
        
        // Change date to Feb 28 2020 and time to 23:53:55
        input_day = 8'd28;
        input_month = 8'd2;
        input_year = 16'd2020;
        #1 set_date = 1;
        #1 set_date = 0;
        
        input_hour = 8'd23;
        input_min = 8'd59;
        input_sec = 8'd57;
        #1 set_time = 1;
        $display("Set date to Feb 28 2020, time to 23:59:57 at %0ds", $time);
        #1 set_time = 0;
        
        $display("Waiting for next day to start...");
        #4;
        $display("Next day started at %0ds", $time);
        // Wait 10 seconds
        hour_format = 0;
        $display("Change to 24-Hour format");
        #10;

        // Set an alarm for 00:00:30
        $display("Set alarm for 00:00:30 at %0ds", $time);
        alarm_input_hour = 8'd0;
        alarm_input_min = 8'd0;
        alarm_input_sec = 8'd30;
        #1 set_alarm = 1;
        #1 set_alarm = 0;
        
        // Wait for alarm to trigger (should be in about 20 seconds)
        wait(alarm_buzzer);
        $display("Alarm triggered at %0ds", $time);
        
        // Snooze
        #5 snooze_alarm = 1;
        #2 snooze_alarm = 0;
        $display("Alarm snoozed at %0ds", $time);
        
        // Wait 5 seconds and stop alarm
        #5;
        #2 stop_alarm = 1;
        $display("Alarm stopped at %0ds", $time);
        #2 stop_alarm = 0;
        
        // Set a timer for 1 minute (60 seconds)
        timer_input_min = 8'd0;
        timer_input_sec = 8'd2;
        #1 set_timer = 1;
        #1 set_timer = 0;
        #1 start_timer = 1;
        #1 start_timer = 0;
        $display("Set timer for 2 seconds at %0ds", $time);
        
        #5 stop_timer = 1;
        // End simulation
        #1 $finish;
    end
    
    // Monitor the clock outputs
    initial begin
        $monitor("Time: %0ds, Date: %0d/%0d/%0d, Time: %0d:%0d:%0d %s, Alarm: %b, Timer: %b",
                 $time,
                 current_day, current_month, current_year,
                 display_hour, display_min, display_sec,
                 am_pm_indicator,
                 alarm_buzzer,
                 timer_buzzer);
    end
       initial begin
       $dumpfile("wave2.vcd");
       $dumpvars(0, clock_tb);
   end
endmodule

EE1501_DSLab/project/final/digital_clock/wave2.vcd
$date
	Thu May  8 09:44:39 2025
$end
$version
	Icarus Verilog
$end
$timescale
	1ms
$end
$scope module clock_tb $end
$var wire 8 ! timer_sec [7:0] $end
$var wire 1 " timer_running $end
$var wire 8 # timer_min [7:0] $end
$var wire 1 $ timer_buzzer $end
$var wire 8 % display_sec [7:0] $end
$var wire 8 & display_min [7:0] $end
$var wire 8 ' display_hour [7:0] $end
$var wire 16 ( current_year [15:0] $end
$var wire 8 ) current_month [7:0] $end
$var wire 8 * current_day [7:0] $end
$var wire 8 + current_24_sec [7:0] $end
$var wire 8 , current_24_min [7:0] $end
$var wire 8 - current_24_hour [7:0] $end
$var wire 1 . alarm_buzzer $end
$var reg 8 / alarm_input_hour [7:0] $end
$var reg 8 0 alarm_input_min [7:0] $end
$var reg 8 1 alarm_input_sec [7:0] $end
$var reg 16 2 am_pm_indicator [15:0] $end
$var reg 1 3 clk $end
$var reg 1 4 hour_format $end
$var reg 8 5 input_day [7:0] $end
$var reg 8 6 input_hour [7:0] $end
$var reg 8 7 input_min [7:0] $end
$var reg 8 8 input_month [7:0] $end
$var reg 8 9 input_sec [7:0] $end
$var reg 16 : input_year [15:0] $end
$var reg 1 ; is_pm $end
$var reg 1 < reset $end
$var reg 1 = set_alarm $end
$var reg 1 > set_date $end
$var reg 1 ? set_time $end
$var reg 1 @ set_timer $end
$var reg 1 A snooze_alarm $end
$var reg 1 B start_timer $end
$var reg 1 C stop_alarm $end
$var reg 1 D stop_timer $end
$var reg 8 E timer_input_min [7:0] $end
$var reg 8 F timer_input_sec [7:0] $end
$scope module dut $end
$var wire 8 G alarm_input_hour [7:0] $end
$var wire 8 H alarm_input_min [7:0] $end
$var wire 8 I alarm_input_sec [7:0] $end
$var wire 1 3 clk $end
$var wire 1 4 hour_format $end
$var wire 8 J input_day [7:0] $end
$var wire 8 K input_hour [7:0] $end
$var wire 8 L input_min [7:0] $end
$var wire 8 M input_month [7:0] $end
$var wire 8 N input_sec [7:0] $end
$var wire 16 O input_year [15:0] $end
$var wire 1 < reset $end
$var wire 1 = set_alarm $end
$var wire 1 > set_date $end
$var wire 1 ? set_time $end
$var wire 1 @ set_timer $end
$var wire 1 A snooze_alarm $end
$var wire 1 B start_timer $end
$var wire 1 C stop_alarm $end
$var wire 1 D stop_timer $end
$var wire 8 P timer_input_min [7:0] $end
$var wire 8 Q timer_input_sec [7:0] $end
$var wire 8 R timer_sec [7:0] $end
$var wire 1 " timer_running $end
$var wire 8 S timer_min [7:0] $end
$var wire 1 $ timer_buzzer $end
$var wire 1 T is_pm $end
$var wire 8 U display_sec [7:0] $end
$var wire 8 V display_min [7:0] $end
$var wire 8 W display_hour [7:0] $end
$var wire 16 X current_year [15:0] $end
$var wire 8 Y current_month [7:0] $end
$var wire 8 Z current_day [7:0] $end
$var wire 8 [ current_24_sec [7:0] $end
$var wire 8 \ current_24_min [7:0] $end
$var wire 8 ] current_24_hour [7:0] $end
$var wire 1 . alarm_buzzer $end
$scope module alarm_module $end
$var wire 8 ^ alarm_input_hour [7:0] $end
$var wire 8 _ alarm_input_min [7:0] $end
$var wire 8 ` alarm_input_sec [7:0] $end
$var wire 1 3 clk $end
$var wire 1 = set_alarm $end
$var wire 1 A snooze_alarm $end
$var wire 1 C stop_alarm $end
$var wire 8 a current_24_sec [7:0] $end
$var wire 8 b current_24_min [7:0] $end
$var wire 8 c current_24_hour [7:0] $end
$var reg 1 . alarm_buzzer $end
$var reg 10 d counter [9:0] $end
$var reg 8 e input_hour_internal [7:0] $end
$var reg 8 f input_min_internal [7:0] $end
$var reg 8 g input_sec_internal [7:0] $end
$var reg 1 h is_buzzing $end
$var reg 1 i is_snoozed $end
$upscope $end
$scope module clock_module $end
$var wire 1 3 clk $end
$var wire 8 j input_hour [7:0] $end
$var wire 8 k input_min [7:0] $end
$var wire 8 l input_sec [7:0] $end
$var wire 1 < reset $end
$var wire 1 ? set_time $end
$var reg 8 m current_24_hour [7:0] $end
$var reg 8 n current_24_min [7:0] $end
$var reg 8 o current_24_sec [7:0] $end
$upscope $end
$scope module date_module $end
$var wire 1 3 clk $end
$var wire 8 p current_24_hour [7:0] $end
$var wire 8 q current_24_min [7:0] $end
$var wire 8 r current_24_sec [7:0] $end
$var wire 8 s input_day [7:0] $end
$var wire 8 t input_month [7:0] $end
$var wire 16 u input_year [15:0] $end
$var wire 1 < reset $end
$var wire 1 > set_date $end
$var reg 8 v current_day [7:0] $end
$var reg 8 w current_month [7:0] $end
$var reg 16 x current_year [15:0] $end
$var reg 8 y days_in_current_month [7:0] $end
$upscope $end
$scope module display_module $end
$var wire 1 3 clk $end
$var wire 8 z current_24_hour [7:0] $end
$var wire 8 { current_24_min [7:0] $end
$var wire 8 | current_24_sec [7:0] $end
$var wire 1 4 hour_format $end
$var wire 8 } timer_sec [7:0] $end
$var wire 1 " timer_running $end
$var wire 8 ~ timer_min [7:0] $end
$var reg 8 !" display_hour [7:0] $end
$var reg 8 "" display_min [7:0] $end
$var reg 8 #" display_sec [7:0] $end
$var reg 1 T is_pm $end
$upscope $end
$scope module timer_module $end
$var wire 1 3 clk $end
$var wire 8 $" input_min [7:0] $end
$var wire 8 %" input_sec [7:0] $end
$var wire 1 < reset $end
$var wire 1 @ set_timer $end
$var wire 1 B start_timer $end
$var wire 1 D stop_timer $end
$var reg 8 &" max_min [7:0] $end
$var reg 1 $ timer_buzzer $end
$var reg 8 '" timer_min [7:0] $end
$var reg 1 " timer_running $end
$var reg 8 (" timer_sec [7:0] $end
$upscope $end
$upscope $end
$upscope $end
$enddefinitions $end
$comment Show the parameter values. $end
$dumpall
$end
#0
$dumpvars
bx ("
bx '"
b1010 &"
b0 %"
b0 $"
bx #"
bx ""
bx !"
bx ~
bx }
bx |
bx {
bx z
bx y
bx x
bx w
bx v
b0 u
b0 t
b0 s
bx r
bx q
bx p
bx o
bx n
bx m
b0 l
b0 k
b0 j
xi
xh
bx g
bx f
bx e
bx d
bx c
bx b
bx a
b0 `
b0 _
b0 ^
bx ]
bx \
bx [
bx Z
bx Y
bx X
bx W
bx V
bx U
xT
bx S
bx R
b0 Q
b0 P
b0 O
b0 N
b0 M
b0 L
b0 K
b0 J
b0 I
b0 H
b0 G
b0 F
b0 E
0D
0C
0B
0A
0@
0?
0>
0=
0<
x;
b0 :
b0 9
b0 8
b0 7
b0 6
b0 5
04
03
b10000000100000 2
b0 1
b0 0
b0 /
x.
bx -
bx ,
bx +
bx *
bx )
bx (
bx '
bx &
bx %
x$
bx #
x"
bx !
$end
#500
0T
0.
13
#1000
0;
0$
0"
b0 !
b0 R
b0 }
b0 ("
b0 #
b0 S
b0 ~
b0 '"
b11111100100 (
b11111100100 X
b11111100100 x
b1 )
b1 Y
b1 w
b1 *
b1 Z
b1 v
b0 -
b0 ]
b0 c
b0 m
b0 p
b0 z
b0 ,
b0 \
b0 b
b0 n
b0 q
b0 {
b0 +
b0 [
b0 a
b0 o
b0 r
b0 |
03
1<
#1500
b0 '
b0 W
b0 !"
b0 &
b0 V
b0 ""
b0 %
b0 U
b0 #"
13
#2000
03
#2500
13
#3000
03
b11111100110 :
b11111100110 O
b11111100110 u
b1100 8
b1100 M
b1100 t
b11111 5
b11111 J
b11111 s
0<
#3500
b1 +
b1 [
b1 a
b1 o
b1 r
b1 |
13
#4000
03
1>
#4500
b1 %
b1 U
b1 #"
b11111100110 (
b11111100110 X
b11111100110 x
b1100 )
b1100 Y
b1100 w
b11111 *
b11111 Z
b11111 v
b10 +
b10 [
b10 a
b10 o
b10 r
b10 |
13
#5000
03
b111010 9
b111010 N
b111010 l
b111011 7
b111011 L
b111011 k
b10111 6
b10111 K
b10111 j
0>
#5500
b10 %
b10 U
b10 #"
b11 +
b11 [
b11 a
b11 o
b11 r
b11 |
13
#6000
03
1?
#6500
1;
b11 %
b11 U
b11 #"
b10111 -
b10111 ]
b10111 c
b10111 m
b10111 p
b10111 z
b111011 ,
b111011 \
b111011 b
b111011 n
b111011 q
b111011 {
b111010 +
b111010 [
b111010 a
b111010 o
b111010 r
b111010 |
13
#7000
03
0?
#7500
b10111 '
b10111 W
b10111 !"
b111011 &
b111011 V
b111011 ""
b111010 %
b111010 U
b111010 #"
b111011 +
b111011 [
b111011 a
b111011 o
b111011 r
b111011 |
13
#8000
03
#8500
0;
b111011 %
b111011 U
b111011 #"
b11111100111 (
b11111100111 X
b11111100111 x
b1 )
b1 Y
b1 w
b1 *
b1 Z
b1 v
b0 -
b0 ]
b0 c
b0 m
b0 p
b0 z
b0 ,
b0 \
b0 b
b0 n
b0 q
b0 {
b0 +
b0 [
b0 a
b0 o
b0 r
b0 |
b11111 y
13
#9000
03
#9500
b0 '
b0 W
b0 !"
b0 &
b0 V
b0 ""
b0 %
b0 U
b0 #"
b1 +
b1 [
b1 a
b1 o
b1 r
b1 |
13
#10000
b100000101001101 2
03
14
#10500
b1100 '
b1100 W
b1100 !"
b1 %
b1 U
b1 #"
b10 +
b10 [
b10 a
b10 o
b10 r
b10 |
13
#11000
03
#11500
b10 %
b10 U
b10 #"
b11 +
b11 [
b11 a
b11 o
b11 r
b11 |
13
#12000
03
#12500
b11 %
b11 U
b11 #"
b100 +
b100 [
b100 a
b100 o
b100 r
b100 |
13
#13000
03
#13500
b100 %
b100 U
b100 #"
b101 +
b101 [
b101 a
b101 o
b101 r
b101 |
13
#14000
03
#14500
b101 %
b101 U
b101 #"
b110 +
b110 [
b110 a
b110 o
b110 r
b110 |
13
#15000
03
#15500
b110 %
b110 U
b110 #"
b111 +
b111 [
b111 a
b111 o
b111 r
b111 |
13
#16000
03
#16500
b111 %
b111 U
b111 #"
b1000 +
b1000 [
b1000 a
b1000 o
b1000 r
b1000 |
13
#17000
03
#17500
b1000 %
b1000 U
b1000 #"
b1001 +
b1001 [
b1001 a
b1001 o
b1001 r
b1001 |
13
#18000
03
#18500
b1001 %
b1001 U
b1001 #"
b1010 +
b1010 [
b1010 a
b1010 o
b1010 r
b1010 |
13
#19000
03
#19500
b1010 %
b1010 U
b1010 #"
b1011 +
b1011 [
b1011 a
b1011 o
b1011 r
b1011 |
13
#20000
03
b11111100100 :
b11111100100 O
b11111100100 u
b10 8
b10 M
b10 t
b11100 5
b11100 J
b11100 s
#20500
b1011 %
b1011 U
b1011 #"
b1100 +
b1100 [
b1100 a
b1100 o
b1100 r
b1100 |
13
#21000
03
1>
#21500
b1100 %
b1100 U
b1100 #"
b1101 +
b1101 [
b1101 a
b1101 o
b1101 r
b1101 |
b11111100100 (
b11111100100 X
b11111100100 x
b10 )
b10 Y
b10 w
b11100 *
b11100 Z
b11100 v
13
#22000
03
b111001 9
b111001 N
b111001 l
0>
#22500
b1101 %
b1101 U
b1101 #"
b1110 +
b1110 [
b1110 a
b1110 o
b1110 r
b1110 |
13
#23000
03
1?
#23500
b101000001001101 2
1;
b1110 %
b1110 U
b1110 #"
b10111 -
b10111 ]
b10111 c
b10111 m
b10111 p
b10111 z
b111011 ,
b111011 \
b111011 b
b111011 n
b111011 q
b111011 {
b111001 +
b111001 [
b111001 a
b111001 o
b111001 r
b111001 |
13
#24000
03
0?
#24500
1T
b1011 '
b1011 W
b1011 !"
b111011 &
b111011 V
b111011 ""
b111001 %
b111001 U
b111001 #"
b111010 +
b111010 [
b111010 a
b111010 o
b111010 r
b111010 |
13
#25000
03
#25500
b111010 %
b111010 U
b111010 #"
b111011 +
b111011 [
b111011 a
b111011 o
b111011 r
b111011 |
13
#26000
03
#26500
b100000101001101 2
0;
b111011 %
b111011 U
b111011 #"
b11101 *
b11101 Z
b11101 v
b0 -
b0 ]
b0 c
b0 m
b0 p
b0 z
b0 ,
b0 \
b0 b
b0 n
b0 q
b0 {
b0 +
b0 [
b0 a
b0 o
b0 r
b0 |
b11101 y
13
#27000
03
#27500
0T
b1100 '
b1100 W
b1100 !"
b0 &
b0 V
b0 ""
b0 %
b0 U
b0 #"
b1 +
b1 [
b1 a
b1 o
b1 r
b1 |
13
#28000
b10000000100000 2
03
04
#28500
b0 '
b0 W
b0 !"
b1 %
b1 U
b1 #"
b10 +
b10 [
b10 a
b10 o
b10 r
b10 |
13
#29000
03
#29500
b10 %
b10 U
b10 #"
b11 +
b11 [
b11 a
b11 o
b11 r
b11 |
13
#30000
03
#30500
b11 %
b11 U
b11 #"
b100 +
b100 [
b100 a
b100 o
b100 r
b100 |
13
#31000
03
#31500
b100 %
b100 U
b100 #"
b101 +
b101 [
b101 a
b101 o
b101 r
b101 |
13
#32000
03
#32500
b101 %
b101 U
b101 #"
b110 +
b110 [
b110 a
b110 o
b110 r
b110 |
13
#33000
03
#33500
b110 %
b110 U
b110 #"
b111 +
b111 [
b111 a
b111 o
b111 r
b111 |
13
#34000
03
#34500
b111 %
b111 U
b111 #"
b1000 +
b1000 [
b1000 a
b1000 o
b1000 r
b1000 |
13
#35000
03
#35500
b1000 %
b1000 U
b1000 #"
b1001 +
b1001 [
b1001 a
b1001 o
b1001 r
b1001 |
13
#36000
03
#36500
b1001 %
b1001 U
b1001 #"
b1010 +
b1010 [
b1010 a
b1010 o
b1010 r
b1010 |
13
#37000
03
#37500
b1010 %
b1010 U
b1010 #"
b1011 +
b1011 [
b1011 a
b1011 o
b1011 r
b1011 |
13
#38000
03
b11110 1
b11110 I
b11110 `
#38500
b1011 %
b1011 U
b1011 #"
b1100 +
b1100 [
b1100 a
b1100 o
b1100 r
b1100 |
13
#39000
03
1=
#39500
b0 d
0h
0i
b0 e
b0 f
b11110 g
b1100 %
b1100 U
b1100 #"
b1101 +
b1101 [
b1101 a
b1101 o
b1101 r
b1101 |
13
#40000
03
0=
#40500
b1101 %
b1101 U
b1101 #"
b1110 +
b1110 [
b1110 a
b1110 o
b1110 r
b1110 |
13
#41000
03
#41500
b1110 %
b1110 U
b1110 #"
b1111 +
b1111 [
b1111 a
b1111 o
b1111 r
b1111 |
13
#42000
03
#42500
b1111 %
b1111 U
b1111 #"
b10000 +
b10000 [
b10000 a
b10000 o
b10000 r
b10000 |
13
#43000
03
#43500
b10000 %
b10000 U
b10000 #"
b10001 +
b10001 [
b10001 a
b10001 o
b10001 r
b10001 |
13
#44000
03
